{
  "timestamp": "2026-03-04T22:34:53.368Z",
  "eventId": "9",
  "season": 2026,
  "tournament": "Arnold Palmer Invitational",
  "weights": {
    "groupWeights": {
      "Driving Performance": 0.1274855796045752,
      "Approach - Short (<100)": 0.06900433214013972,
      "Approach - Mid (100-150)": 0.08965522775497517,
      "Approach - Long (150-200)": 0.09938524345765187,
      "Approach - Very Long (>200)": 0.07912098487603479,
      "Putting": 0.1182983809354761,
      "Around the Green": 0.08366624145697521,
      "Scoring": 0.21010678696539653,
      "Course Management": 0.12327722280877546
    },
    "metricWeights": {
      "Driving Performance::Driving Distance": 0.37272464200468447,
      "Driving Performance::Driving Accuracy": 0.19504930034467305,
      "Driving Performance::SG OTT": 0.4322260576506426,
      "Approach - Short (<100)::Approach <100 GIR": 0.5450040177268823,
      "Approach - Short (<100)::Approach <100 SG": 0.2889009072621895,
      "Approach - Short (<100)::Approach <100 Prox": 0.16609507501092818,
      "Approach - Mid (100-150)::Approach <150 FW GIR": 0.17722771909057,
      "Approach - Mid (100-150)::Approach <150 FW SG": 0.22846788373494242,
      "Approach - Mid (100-150)::Approach <150 FW Prox": 0.11707074834980667,
      "Approach - Mid (100-150)::Approach <150 Rough GIR": 0.1994163178860937,
      "Approach - Mid (100-150)::Approach <150 Rough SG": 0.20375772142895038,
      "Approach - Mid (100-150)::Approach <150 Rough Prox": 0.07405960950963689,
      "Approach - Long (150-200)::Approach <200 FW GIR": 0.23141762315144132,
      "Approach - Long (150-200)::Approach <200 FW SG": 0.259401161982007,
      "Approach - Long (150-200)::Approach <200 FW Prox": 0.09905479835126244,
      "Approach - Long (150-200)::Approach >150 Rough GIR": 0.1928363126947251,
      "Approach - Long (150-200)::Approach >150 Rough SG": 0.1752159717653237,
      "Approach - Long (150-200)::Approach >150 Rough Prox": 0.04207413205524048,
      "Approach - Very Long (>200)::Approach >200 FW GIR": 0.3060394232794304,
      "Approach - Very Long (>200)::Approach >200 FW SG": 0.36895714936800134,
      "Approach - Very Long (>200)::Approach >200 FW Prox": 0.32500342735256826,
      "Putting::SG Putting": 1,
      "Around the Green::SG Around Green": 1,
      "Scoring::SG T2G": 0.38787954585028306,
      "Scoring::Scoring Average": 0.3167039645688216,
      "Scoring::Birdie Chances Created": 0.07653030198477906,
      "Scoring::Scoring: Approach <100 SG": 0.020117411846995715,
      "Scoring::Scoring: Approach <150 FW SG": 0.026130768649086825,
      "Scoring::Scoring: Approach <150 Rough SG": 0.026130768649086825,
      "Scoring::Scoring: Approach <200 FW SG": 0.08200032002851514,
      "Scoring::Scoring: Approach >200 FW SG": 0.03225345921121595,
      "Scoring::Scoring: Approach >150 Rough SG": 0.03225345921121595,
      "Course Management::Scrambling": 0.36572235006292175,
      "Course Management::Great Shots": 0.10543895395825442,
      "Course Management::Poor Shots": 0.2947214008294547,
      "Course Management::Course Management: Approach <100 Prox": 0.021517273879862086,
      "Course Management::Course Management: Approach <150 FW Prox": 0.027949067702646945,
      "Course Management::Course Management: Approach <150 Rough Prox": 0.027949067702646945,
      "Course Management::Course Management: Approach >150 Rough Prox": 0.034497803231300625,
      "Course Management::Course Management: Approach <200 FW Prox": 0.08770627940161176,
      "Course Management::Course Management: Approach >200 FW Prox": 0.034497803231300625
    }
  },
  "players": [
    {
      "rank": 1,
      "dgId": "13900",
      "name": "Lowry, Shane",
      "refinedWeightedScore": 0.9143425038926829,
      "weightedScore": 0.9143425038926829,
      "compositeScore": 0.787295489346371,
      "war": 0.49085245540497635,
      "dataCoverage": 1,
      "confidenceFactor": 1,
      "teeTimeMultiplier": null,
      "teeTimeMinutes": null,
      "notes": "ًں’ھ SG Putting, SG T2G | ًں‘چ Good course fit | â†“ Around green | For Course Setup - خ”Predâ†“ خ”Trendâ†’ | BucketSig â†‘ z=1.25 (0.139) [Sâ†‘ Mâ†‘ Lâ†“ VLâ†‘] | ًںŒ¦ï¸ڈ Weather wave: R1 AM, R2 PM (penalty=0.04)"
    },
    {
      "rank": 2,
      "dgId": "22833",
      "name": "Echavarria, Nico",
      "refinedWeightedScore": 0.8778148227154449,
      "weightedScore": 0.8778148227154449,
      "compositeScore": 0.7545574223827489,
      "war": 0.4669568216064585,
      "dataCoverage": 0.936910569105691,
      "confidenceFactor": 1,
      "teeTimeMultiplier": null,
      "teeTimeMinutes": null,
      "notes": "ًں’ھ SG Putting, SG T2G | ًں‘چ Good course fit | â†‘ Tee-to-green | For Course Setup - خ”Predâ†’ خ”Trendâ†’ | BucketSig â†‘ z=0.54 (0.020) [Sâ†‘ Mâ†‘ Lâ†“ VLâ†“]"
    },
    {
      "rank": 3,
      "dgId": "23602",
      "name": "Hojgaard, Nicolai",
      "refinedWeightedScore": 0.8570746265890871,
      "weightedScore": 0.8570746265890871,
      "compositeScore": 0.7457598981233412,
      "war": 0.4860255317032677,
      "dataCoverage": 1,
      "confidenceFactor": 1,
      "teeTimeMultiplier": null,
      "teeTimeMinutes": null,
      "notes": "ًں’ھ SG Putting, SG T2G | ًں‘چ Good course fit | â†‘ Putting | For Course Setup - خ”Predâ†‘ خ”Trendâ†‘ | BucketSig â†‘ z=3.89 (0.578) [Sâ†‘ Mâ†“ Lâ†‘ VLâ†“]"
    },
    {
      "rank": 4,
      "dgId": "18417",
      "name": "Scheffler, Scottie",
      "refinedWeightedScore": 0.7560865752651064,
      "weightedScore": 0.7560865752651064,
      "compositeScore": 0.671505818426898,
      "war": 0.4741507191377454,
      "dataCoverage": 1,
      "confidenceFactor": 1,
      "teeTimeMultiplier": null,
      "teeTimeMinutes": null,
      "notes": "ًں’ھ SG Around Green, SG Putting | âœ… Strong course fit | â†‘ Putting | For Course Setup - خ”Predâ†’ خ”Trendâ†’ | BucketSig â†‘ z=0.20 (-0.036) [Sâ†“ Mâ†“ Lâ†‘ VLâ†“] | ًںŒ¦ï¸ڈ Weather wave: R1 AM, R2 PM (penalty=0.04)"
    },
    {
      "rank": 5,
      "dgId": "14577",
      "name": "English, Harris",
      "refinedWeightedScore": 0.5810899044614184,
      "weightedScore": 0.5810899044614184,
      "compositeScore": 0.5025655277102256,
      "war": 0.31934198195744257,
      "dataCoverage": 1,
      "confidenceFactor": 1,
      "teeTimeMultiplier": null,
      "teeTimeMinutes": null,
      "notes": "ًں’ھ SG Putting, SG T2G | ًں‘چ Good course fit | â†“ Approach | For Course Setup - خ”Predâ†’ خ”Trendâ†’ | BucketSig â†‘ z=0.97 (0.093) [Sâ†“ Mâ†“ Lâ†‘ VLâ†‘] | ًںŒ¦ï¸ڈ Weather wave: R1 AM, R2 PM (penalty=0.04)"
    },
    {
      "rank": 6,
      "dgId": "21944",
      "name": "Moore, Taylor",
      "refinedWeightedScore": 0.5367058012453939,
      "weightedScore": 0.5367058012453939,
      "compositeScore": 0.47355677362891835,
      "war": 0.3262090425238089,
      "dataCoverage": 1,
      "confidenceFactor": 1,
      "teeTimeMultiplier": null,
      "teeTimeMinutes": null,
      "notes": "ًں’ھ SG Around Green, SG Putting | âœ… Strong course fit | â„¹ï¸ڈ Recent bucket trend weak (short-term) despite baseline fit | â†‘ Putting | For Course Setup - خ”Predâ†’ خ”Trendâ†’ | BucketSig â†“ z=-0.01 (-0.071) [Sâ†“ Mâ†“ Lâ†“ VLâ†‘] | ًںŒ¦ï¸ڈ Weather wave: R1 AM, R2 PM (penalty=0.04)"
    },
    {
      "rank": 7,
      "dgId": "22985",
      "name": "Smotherman, Austin",
      "refinedWeightedScore": 0.4472514793321743,
      "weightedScore": 0.4472514793321743,
      "compositeScore": 0.4210500788165158,
      "war": 0.3599134776133126,
      "dataCoverage": 1,
      "confidenceFactor": 1,
      "teeTimeMultiplier": null,
      "teeTimeMinutes": null,
      "notes": "ًں’ھ SG T2G, Approach <100 GIR | ًں‘چ Good course fit | â†“ Around green | For Course Setup - خ”Predâ†“ خ”Trendâ†’ | BucketSig â†“ z=-0.73 (-0.190) [Sâ†’ Mâ†“ Lâ†“ VLâ†“]"
    },
    {
      "rank": 8,
      "dgId": "12294",
      "name": "Fleetwood, Tommy",
      "refinedWeightedScore": 0.47391694596913914,
      "weightedScore": 0.47391694596913914,
      "compositeScore": 0.4208799705503122,
      "war": 0.29712702790638273,
      "dataCoverage": 0.8422764227642277,
      "confidenceFactor": 1,
      "teeTimeMultiplier": null,
      "teeTimeMinutes": null,
      "notes": "ًں’ھ SG Around Green, SG Putting | âœ… Strong course fit | â†“ Approach | For Course Setup - خ”Predâ†’ خ”Trendâ†’ | BucketSig â†‘ z=0.61 (0.032) [Sâ†“ Mâ†“ Lâ†“ VLâ†‘]"
    },
    {
      "rank": 9,
      "dgId": "14609",
      "name": "Kim, Si Woo",
      "refinedWeightedScore": 0.4311791532357303,
      "weightedScore": 0.4311791532357303,
      "compositeScore": 0.3821708959989644,
      "war": 0.26781829577984423,
      "dataCoverage": 1,
      "confidenceFactor": 1,
      "teeTimeMultiplier": null,
      "teeTimeMinutes": null,
      "notes": "ًں’ھ SG T2G | âڑ ï¸ڈ Poor course fit | â„¹ï¸ڈ Recent bucket trend strong (short-term) despite baseline fit | â†“ Off tee | For Course Setup - خ”Predâ†‘ خ”Trendâ†‘ | BucketSig â†‘ z=1.46 (0.174) [Sâ†“ Mâ†‘ Lâ†‘ VLâ†‘]"
    },
    {
      "rank": 10,
      "dgId": "21891",
      "name": "Kitayama, Kurt",
      "refinedWeightedScore": 0.44459022731629344,
      "weightedScore": 0.44459022731629344,
      "compositeScore": 0.36848948997484116,
      "war": 0.1909211028447859,
      "dataCoverage": 1,
      "confidenceFactor": 1,
      "teeTimeMultiplier": null,
      "teeTimeMinutes": null,
      "notes": "ًں’ھ SG T2G, SG OTT | â†‘ Putting | For Course Setup - خ”Predâ†’ خ”Trendâ†‘ | BucketSig â†‘ z=1.31 (0.149) [Sâ†“ Mâ†“ Lâ†‘ VLâ†‘]"
    },
    {
      "rank": 11,
      "dgId": "10091",
      "name": "McIlroy, Rory",
      "refinedWeightedScore": 0.3665577152651517,
      "weightedScore": 0.3665577152651517,
      "compositeScore": 0.3580540740987993,
      "war": 0.3382122447106438,
      "dataCoverage": 0.8422764227642277,
      "confidenceFactor": 1,
      "teeTimeMultiplier": null,
      "teeTimeMinutes": null,
      "notes": "ًں’ھ SG Around Green, SG OTT | âœ… Strong course fit | â„¹ï¸ڈ Recent bucket trend weak (short-term) despite baseline fit | â†‘ Around green | For Course Setup - خ”Predâ†’ خ”Trendâ†“ | BucketSig â†“ z=-1.06 (-0.246) [Sâ†“ Mâ†‘ Lâ†“ VLâ†‘]"
    },
    {
      "rank": 12,
      "dgId": "19895",
      "name": "Schauffele, Xander",
      "refinedWeightedScore": 0.3427753172643514,
      "weightedScore": 0.3427753172643514,
      "compositeScore": 0.32159328347441235,
      "war": 0.2721685379645546,
      "dataCoverage": 1,
      "confidenceFactor": 1,
      "teeTimeMultiplier": null,
      "teeTimeMinutes": null,
      "notes": "ًں’ھ SG OTT, SG T2G | â†“ Around green | For Course Setup - خ”Predâ†’ خ”Trendâ†’ | BucketSig â†“ z=-0.29 (-0.117) [Sâ†‘ Mâ†“ Lâ†“ VLâ†’] | ًںŒ¦ï¸ڈ Weather wave: R1 AM, R2 PM (penalty=0.04)"
    },
    {
      "rank": 13,
      "dgId": "17365",
      "name": "Mitchell, Keith",
      "refinedWeightedScore": 0.31093940288248323,
      "weightedScore": 0.31093940288248323,
      "compositeScore": 0.29717163709180655,
      "war": 0.26504685024689434,
      "dataCoverage": 0.936910569105691,
      "confidenceFactor": 1,
      "teeTimeMultiplier": null,
      "teeTimeMinutes": null,
      "notes": "ًں’ھ SG OTT, SG T2G | â†“ Around green | For Course Setup - خ”Predâ†‘ خ”Trendâ†’ | BucketSig â†‘ z=0.21 (-0.035) [Sâ†‘ Mâ†“ Lâ†‘ VLâ†“] | ًںŒ¦ï¸ڈ Weather wave: R1 AM, R2 PM (penalty=0.04)"
    },
    {
      "rank": 14,
      "dgId": "18634",
      "name": "McNealy, Maverick",
      "refinedWeightedScore": 0.27920029144791575,
      "weightedScore": 0.27920029144791575,
      "compositeScore": 0.2609934584870754,
      "war": 0.21851084824511463,
      "dataCoverage": 1,
      "confidenceFactor": 1,
      "teeTimeMultiplier": null,
      "teeTimeMinutes": null,
      "notes": "ًں’ھ SG OTT | âڑ ï¸ڈ Poor course fit | â†“ Putting | For Course Setup - خ”Predâ†’ خ”Trendâ†’ | BucketSig â†“ z=-0.37 (-0.131) [Sâ†’ Mâ†“ Lâ†“ VLâ†‘]"
    },
    {
      "rank": 15,
      "dgId": "10419",
      "name": "Noren, Alex",
      "refinedWeightedScore": 0.27319999046313703,
      "weightedScore": 0.27319999046313703,
      "compositeScore": 0.25390875516038164,
      "war": 0.2088958727872857,
      "dataCoverage": 1,
      "confidenceFactor": 1,
      "teeTimeMultiplier": null,
      "teeTimeMinutes": null,
      "notes": "ًں’ھ SG Around Green, SG Putting | âœ… Strong course fit | â†‘ Off tee | For Course Setup - خ”Predâ†’ خ”Trendâ†’ | BucketSig â†‘ z=0.19 (-0.037) [Sâ†“ Mâ†“ Lâ†‘ VLâ†“] | ًںŒ¦ï¸ڈ Weather wave: R1 AM, R2 PM (penalty=0.04)"
    },
    {
      "rank": 16,
      "dgId": "29767",
      "name": "Gerard, Ryan",
      "refinedWeightedScore": 0.3005439095366769,
      "weightedScore": 0.3005439095366769,
      "compositeScore": 0.2537852317080832,
      "war": 0.1446816501080312,
      "dataCoverage": 1,
      "confidenceFactor": 1,
      "teeTimeMultiplier": null,
      "teeTimeMinutes": null,
      "notes": "ًں’ھ SG OTT, SG T2G | âڑ ï¸ڈ Poor course fit | â„¹ï¸ڈ Recent bucket trend strong (short-term) despite baseline fit | â†“ Putting | For Course Setup - خ”Predâ†‘ خ”Trendâ†‘ | BucketSig â†‘ z=2.34 (0.320) [Sâ†“ Mâ†‘ Lâ†‘ VLâ†“]"
    },
    {
      "rank": 17,
      "dgId": "19396",
      "name": "Knapp, Jake",
      "refinedWeightedScore": 0.2468607411573974,
      "weightedScore": 0.2468607411573974,
      "compositeScore": 0.2535370700853921,
      "war": 0.2691151709173799,
      "dataCoverage": 1,
      "confidenceFactor": 1,
      "teeTimeMultiplier": null,
      "teeTimeMinutes": null,
      "notes": "ًں’ھ SG Putting | ًں‘چ Good course fit | â†‘ Approach | For Course Setup - خ”Predâ†’ خ”Trendâ†’ | BucketSig â†“ z=-1.11 (-0.254) [Sâ†‘ Mâ†‘ Lâ†“ VLâ†“]"
    },
    {
      "rank": 18,
      "dgId": "17646",
      "name": "Fitzpatrick, Matt",
      "refinedWeightedScore": 0.24180637940289976,
      "weightedScore": 0.24180637940289976,
      "compositeScore": 0.2417602562288536,
      "war": 0.24165263548941265,
      "dataCoverage": 1,
      "confidenceFactor": 1,
      "teeTimeMultiplier": null,
      "teeTimeMinutes": null,
      "notes": "ًں’ھ SG T2G | â†‘ Putting | For Course Setup - خ”Predâ†’ خ”Trendâ†’ | BucketSig â†“ z=-0.45 (-0.145) [Sâ†“ Mâ†“ Lâ†“ VLâ†‘]"
    },
    {
      "rank": 19,
      "dgId": "14636",
      "name": "Spieth, Jordan",
      "refinedWeightedScore": 0.2428920434542032,
      "weightedScore": 0.2428920434542032,
      "compositeScore": 0.22225040974162596,
      "war": 0.17408659774561247,
      "dataCoverage": 1,
      "confidenceFactor": 1,
      "teeTimeMultiplier": null,
      "teeTimeMinutes": null,
      "notes": "ًں’ھ SG Putting, SG Around Green | âœ… Strong course fit | â„¹ï¸ڈ Recent bucket trend weak (short-term) despite baseline fit | â†“ Total game | For Course Setup - خ”Predâ†“ خ”Trendâ†“ | BucketSig â†“ z=-1.40 (-0.303) [Sâ†“ Mâ†“ Lâ†“ VLâ†‘]"
    },
    {
      "rank": 20,
      "dgId": "16841",
      "name": "Lee, Min Woo",
      "refinedWeightedScore": 0.22308834991246654,
      "weightedScore": 0.22308834991246654,
      "compositeScore": 0.21775458744760356,
      "war": 0.2053091416962567,
      "dataCoverage": 1,
      "confidenceFactor": 1,
      "teeTimeMultiplier": null,
      "teeTimeMinutes": null,
      "notes": "ًں’ھ SG Putting, SG Around Green | âœ… Strong course fit | â„¹ï¸ڈ Recent bucket trend weak (short-term) despite baseline fit | â†‘ Approach | For Course Setup - خ”Predâ†’ خ”Trendâ†’ | BucketSig â†“ z=-0.90 (-0.219) [Sâ†“ Mâ†“ Lâ†“ VLâ†“] | ًںŒ¦ï¸ڈ Weather wave: R1 AM, R2 PM (penalty=0.04)"
    },
    {
      "rank": 21,
      "dgId": "30332",
      "name": "Bennett, Daniel",
      "refinedWeightedScore": 0.1717268088373858,
      "weightedScore": 0.858634044186929,
      "compositeScore": 0.5383798348895628,
      "war": -0.20887998680429154,
      "dataCoverage": 0,
      "confidenceFactor": 0.2,
      "teeTimeMultiplier": null,
      "teeTimeMinutes": null,
      "notes": "âڑ ï¸ڈ Limited data (0%) | For Course Setup - خ”Predâˆ… خ”Trendâˆ… | ًںŒ¦ï¸ڈ Weather wave: R1 AM, R2 PM (penalty=0.04)"
    },
    {
      "rank": 22,
      "dgId": "6430",
      "name": "Scott, Adam",
      "refinedWeightedScore": 0.17039199305163719,
      "weightedScore": 0.17039199305163719,
      "compositeScore": 0.1728679008111026,
      "war": 0.17864501891652193,
      "dataCoverage": 1,
      "confidenceFactor": 1,
      "teeTimeMultiplier": null,
      "teeTimeMinutes": null,
      "notes": "ًں’ھ SG Putting, SG OTT | ًں‘چ Good course fit | â†“ Putting | For Course Setup - خ”Predâ†’ خ”Trendâ†’ | BucketSig â†“ z=-0.01 (-0.071) [Sâ†“ Mâ†“ Lâ†“ VLâ†“] | ًںŒ¦ï¸ڈ Weather wave: R1 AM, R2 PM (penalty=0.04)"
    },
    {
      "rank": 23,
      "dgId": "29433",
      "name": "Bridgeman, Jacob",
      "refinedWeightedScore": 0.13760038811817982,
      "weightedScore": 0.13760038811817982,
      "compositeScore": 0.14872346813129572,
      "war": 0.17467732149523288,
      "dataCoverage": 1,
      "confidenceFactor": 1,
      "teeTimeMultiplier": null,
      "teeTimeMinutes": null,
      "notes": "âڑ ï¸ڈ Poor course fit | â†‘ Around green | For Course Setup - خ”Predâ†’ خ”Trendâ†’ | BucketSig â†“ z=-0.10 (-0.085) [Sâ†“ Mâ†“ Lâ†“ VLâ†’]"
    },
    {
      "rank": 24,
      "dgId": "22085",
      "name": "Morikawa, Collin",
      "refinedWeightedScore": 0.12411155550108198,
      "weightedScore": 0.12411155550108198,
      "compositeScore": 0.13949357685515823,
      "war": 0.17538496001466947,
      "dataCoverage": 1,
      "confidenceFactor": 1,
      "teeTimeMultiplier": null,
      "teeTimeMinutes": null,
      "notes": "ًں’ھ SG Around Green | ًں‘چ Good course fit | â†“ Around green | For Course Setup - خ”Predâ†’ خ”Trendâ†’ | BucketSig â†“ z=-0.50 (-0.152) [Sâ†“ Mâ†“ Lâ†“ VLâ†‘] | ًںŒ¦ï¸ڈ Weather wave: R1 AM, R2 PM (penalty=0.04)"
    },
    {
      "rank": 25,
      "dgId": "11889",
      "name": "Fox, Ryan",
      "refinedWeightedScore": 0.12043715912858385,
      "weightedScore": 0.12043715912858385,
      "compositeScore": 0.13213901470155393,
      "war": 0.15944334437181745,
      "dataCoverage": 1,
      "confidenceFactor": 1,
      "teeTimeMultiplier": null,
      "teeTimeMinutes": null,
      "notes": "ًں’ھ SG Around Green | ًں‘چ Good course fit | â†“ Total game | For Course Setup - خ”Predâ†’ خ”Trendâ†’ | BucketSig â†“ z=-0.11 (-0.088) [Sâ†‘ Mâ†‘ Lâ†“ VLâ†‘] | ًںŒ¦ï¸ڈ Weather wave: R1 AM, R2 PM (penalty=0.04)"
    },
    {
      "rank": 26,
      "dgId": "27900",
      "name": "Potgieter, Aldrich",
      "refinedWeightedScore": 0.1597544108410614,
      "weightedScore": 0.1597544108410614,
      "compositeScore": 0.12537173336370078,
      "war": 0.04514548591652599,
      "dataCoverage": 1,
      "confidenceFactor": 1,
      "teeTimeMultiplier": null,
      "teeTimeMinutes": null,
      "notes": "ًں’ھ SG Putting, SG OTT | ًں‘چ Good course fit | â†‘ Putting | For Course Setup - خ”Predâ†’ خ”Trendâ†’ | BucketSig â†‘ z=0.62 (0.035) [Sâ†“ Mâ†“ Lâ†‘ VLâ†‘] | ًںŒ¦ï¸ڈ Weather wave: R1 AM, R2 PM (penalty=0.04)"
    },
    {
      "rank": 27,
      "dgId": "12965",
      "name": "Fowler, Rickie",
      "refinedWeightedScore": 0.15164892145942427,
      "weightedScore": 0.15164892145942427,
      "compositeScore": 0.12052210336205717,
      "war": 0.04789286113486727,
      "dataCoverage": 1,
      "confidenceFactor": 1,
      "teeTimeMultiplier": null,
      "teeTimeMinutes": null,
      "notes": "ًں’ھ SG Putting, SG OTT | ًں‘چ Good course fit | â†‘ Around green | For Course Setup - خ”Predâ†’ خ”Trendâ†’ | BucketSig â†‘ z=0.77 (0.059) [Sâ†“ Mâ†“ Lâ†‘ VLâ†‘]"
    },
    {
      "rank": 28,
      "dgId": "26651",
      "name": "Young, Cameron",
      "refinedWeightedScore": 0.12491369866660604,
      "weightedScore": 0.12491369866660604,
      "compositeScore": 0.11462017083740988,
      "war": 0.09060193923595221,
      "dataCoverage": 1,
      "confidenceFactor": 1,
      "teeTimeMultiplier": null,
      "teeTimeMinutes": null,
      "notes": "â†‘ Approach | For Course Setup - خ”Predâ†’ خ”Trendâ†’ | BucketSig â†‘ z=0.45 (0.005) [Sâ†‘ Mâ†“ Lâ†“ VLâ†‘] | ًںŒ¦ï¸ڈ Weather wave: R1 AM, R2 PM (penalty=0.04)"
    },
    {
      "rank": 29,
      "dgId": "24968",
      "name": "Griffin, Ben",
      "refinedWeightedScore": 0.08556641260929444,
      "weightedScore": 0.08556641260929444,
      "compositeScore": 0.09238548178112477,
      "war": 0.10829664318206218,
      "dataCoverage": 1,
      "confidenceFactor": 1,
      "teeTimeMultiplier": null,
      "teeTimeMinutes": null,
      "notes": "ًں’ھ SG Putting | ًں‘چ Good course fit | â†“ Tee-to-green | For Course Setup - خ”Predâ†’ خ”Trendâ†’ | BucketSig â†“ z=-0.01 (-0.071) [Sâ†‘ Mâ†“ Lâ†“ VLâ†‘]"
    },
    {
      "rank": 30,
      "dgId": "18841",
      "name": "Hovland, Viktor",
      "refinedWeightedScore": 0.11889471952564208,
      "weightedScore": 0.11889471952564208,
      "compositeScore": 0.0909364780512717,
      "war": 0.025700581277740844,
      "dataCoverage": 1,
      "confidenceFactor": 1,
      "teeTimeMultiplier": null,
      "teeTimeMinutes": null,
      "notes": "âڑ ï¸ڈ Poor course fit | â„¹ï¸ڈ Recent bucket trend strong (short-term) despite baseline fit | â†‘ Putting | For Course Setup - خ”Predâ†‘ خ”Trendâ†‘ | BucketSig â†‘ z=1.06 (0.107) [Sâ†“ Mâ†“ Lâ†‘ VLâ†‘]"
    },
    {
      "rank": 31,
      "dgId": "17606",
      "name": "Berger, Daniel",
      "refinedWeightedScore": 0.11158668436399946,
      "weightedScore": 0.11158668436399946,
      "compositeScore": 0.08383738870191802,
      "war": 0.01908903215706139,
      "dataCoverage": 1,
      "confidenceFactor": 1,
      "teeTimeMultiplier": null,
      "teeTimeMinutes": null,
      "notes": "âڑ ï¸ڈ Poor course fit | â„¹ï¸ڈ Recent bucket trend strong (short-term) despite baseline fit | â†“ Off tee | For Course Setup - خ”Predâ†‘ خ”Trendâ†’ | BucketSig â†‘ z=1.29 (0.145) [Sâ†’ Mâ†‘ Lâ†“ VLâ†‘] | ًںŒ¦ï¸ڈ Weather wave: R1 AM, R2 PM (penalty=0.04)"
    },
    {
      "rank": 32,
      "dgId": "13562",
      "name": "Matsuyama, Hideki",
      "refinedWeightedScore": 0.06182133061078761,
      "weightedScore": 0.06182133061078761,
      "compositeScore": 0.06042558184275414,
      "war": 0.057168834717342736,
      "dataCoverage": 1,
      "confidenceFactor": 1,
      "teeTimeMultiplier": null,
      "teeTimeMinutes": null,
      "notes": "âڑ ï¸ڈ Poor course fit | â„¹ï¸ڈ Recent bucket trend strong (short-term) despite baseline fit | â†“ Approach | For Course Setup - خ”Predâ†’ خ”Trendâ†’ | BucketSig â†‘ z=0.44 (0.004) [Sâ†’ Mâ†‘ Lâ†“ VLâ†‘]"
    },
    {
      "rank": 33,
      "dgId": "17780",
      "name": "Pendrith, Taylor",
      "refinedWeightedScore": 0.04851083153653493,
      "weightedScore": 0.04851083153653493,
      "compositeScore": 0.05274570992960832,
      "war": 0.06262709284677959,
      "dataCoverage": 1,
      "confidenceFactor": 1,
      "teeTimeMultiplier": null,
      "teeTimeMinutes": null,
      "notes": "ًں’ھ SG OTT | â†‘ Tee-to-green | For Course Setup - خ”Predâ†’ خ”Trendâ†’ | BucketSig â†“ z=-0.21 (-0.104) [Sâ†“ Mâ†“ Lâ†“ VLâ†“]"
    },
    {
      "rank": 34,
      "dgId": "15466",
      "name": "Cantlay, Patrick",
      "refinedWeightedScore": 0.0075402627794147956,
      "weightedScore": 0.0075402627794147956,
      "compositeScore": 0.015222519136867809,
      "war": 0.03314778397092484,
      "dataCoverage": 1,
      "confidenceFactor": 1,
      "teeTimeMultiplier": null,
      "teeTimeMinutes": null,
      "notes": "â†‘ Putting | For Course Setup - خ”Predâ†’ خ”Trendâ†’ | BucketSig â†‘ z=0.18 (-0.039) [Sâ†‘ Mâ†“ Lâ†“ VLâ†‘] | ًںŒ¦ï¸ڈ Weather wave: R1 AM, R2 PM (penalty=0.04)"
    },
    {
      "rank": 35,
      "dgId": "19483",
      "name": "Burns, Sam",
      "refinedWeightedScore": -0.016471270698926004,
      "weightedScore": -0.016471270698926004,
      "compositeScore": 0.004319068292667039,
      "war": 0.052829859273050804,
      "dataCoverage": 1,
      "confidenceFactor": 1,
      "teeTimeMultiplier": null,
      "teeTimeMinutes": null,
      "notes": "ًں’ھ SG Putting, Approach <100 GIR | ًں‘چ Good course fit | â†“ Tee-to-green | For Course Setup - خ”Predâ†’ خ”Trendâ†’ | BucketSig â†“ z=-0.65 (-0.177) [Sâ†“ Mâ†“ Lâ†“ VLâ†‘]"
    },
    {
      "rank": 36,
      "dgId": "17576",
      "name": "Conners, Corey",
      "refinedWeightedScore": -0.03811742108515103,
      "weightedScore": -0.03811742108515103,
      "compositeScore": -0.0086292302904909,
      "war": 0.06017654823038274,
      "dataCoverage": 1,
      "confidenceFactor": 1,
      "teeTimeMultiplier": null,
      "teeTimeMinutes": null,
      "notes": "ًں’ھ SG OTT | âڑ ï¸ڈ Poor course fit | â†“ Approach | For Course Setup - خ”Predâ†’ خ”Trendâ†’ | BucketSig â†“ z=-0.52 (-0.156) [Sâ†‘ Mâ†‘ Lâ†“ VLâ†‘] | ًںŒ¦ï¸ڈ Weather wave: R1 AM, R2 PM (penalty=0.04)"
    },
    {
      "rank": 37,
      "dgId": "14139",
      "name": "Thomas, Justin",
      "refinedWeightedScore": -0.0026402457078992143,
      "weightedScore": -0.013193075444367932,
      "compositeScore": -0.0095632820538058,
      "war": -0.0010937641424941611,
      "dataCoverage": 0.053658536585365846,
      "confidenceFactor": 0.20012359658159343,
      "teeTimeMultiplier": null,
      "teeTimeMinutes": null,
      "notes": "ًں’ھ SG Around Green | ًں‘چ Good course fit | â†“ Putting | âڑ ï¸ڈ Limited data (5%) | For Course Setup - خ”Predâˆ… خ”Trendâˆ…"
    },
    {
      "rank": 38,
      "dgId": "14509",
      "name": "Dahmen, Joel",
      "refinedWeightedScore": -0.03161811432562328,
      "weightedScore": -0.03161811432562328,
      "compositeScore": -0.010353518648787188,
      "war": 0.03926387126383035,
      "dataCoverage": 1,
      "confidenceFactor": 1,
      "teeTimeMultiplier": null,
      "teeTimeMinutes": null,
      "notes": "ًں’ھ SG OTT, SG T2G | âڑ ï¸ڈ Poor course fit | â†‘ Approach | For Course Setup - خ”Predâ†“ خ”Trendâ†“ | BucketSig â†“ z=-3.42 (-0.638) [Sâ†‘ Mâ†“ Lâ†“ VLâ†‘] | ًںŒ¦ï¸ڈ Weather wave: R1 AM, R2 PM (penalty=0.04)"
    },
    {
      "rank": 39,
      "dgId": "23950",
      "name": "Aberg, Ludvig",
      "refinedWeightedScore": -0.04218286320973464,
      "weightedScore": -0.04218286320973464,
      "compositeScore": -0.014775283962483047,
      "war": 0.049175734281104,
      "dataCoverage": 1,
      "confidenceFactor": 1,
      "teeTimeMultiplier": null,
      "teeTimeMinutes": null,
      "notes": "â†“ Approach | For Course Setup - خ”Predâ†’ خ”Trendâ†’ | BucketSig â†“ z=-0.60 (-0.170) [Sâ†“ Mâ†“ Lâ†“ VLâ†‘]"
    },
    {
      "rank": 40,
      "dgId": "28309",
      "name": "Coody, Pierceson",
      "refinedWeightedScore": 0.0020547407695670206,
      "weightedScore": 0.0020547407695670206,
      "compositeScore": -0.02406549096868868,
      "war": -0.08501269835795199,
      "dataCoverage": 1,
      "confidenceFactor": 1,
      "teeTimeMultiplier": null,
      "teeTimeMinutes": null,
      "notes": "ًں’ھ Approach <100 GIR | âڑ ï¸ڈ Poor course fit | â„¹ï¸ڈ Recent bucket trend strong (short-term) despite baseline fit | â†“ Around green | For Course Setup - خ”Predâ†‘ خ”Trendâ†‘ | BucketSig â†‘ z=2.46 (0.340) [Sâ†‘ Mâ†‘ Lâ†‘ VLâ†“]"
    },
    {
      "rank": 41,
      "dgId": "27774",
      "name": "Gotterup, Chris",
      "refinedWeightedScore": -0.02556477745340522,
      "weightedScore": -0.02556477745340522,
      "compositeScore": -0.04709266897962949,
      "war": -0.09732441587415282,
      "dataCoverage": 1,
      "confidenceFactor": 1,
      "teeTimeMultiplier": null,
      "teeTimeMinutes": null,
      "notes": "âڑ ï¸ڈ Poor course fit | â„¹ï¸ڈ Recent bucket trend strong (short-term) despite baseline fit | â†‘ Putting | For Course Setup - خ”Predâ†’ خ”Trendâ†‘ | BucketSig â†‘ z=1.18 (0.128) [Sâ†‘ Mâ†‘ Lâ†‘ VLâ†‘]"
    },
    {
      "rank": 42,
      "dgId": "17488",
      "name": "Im, Sungjae",
      "refinedWeightedScore": -0.027346285167044806,
      "weightedScore": -0.13664698033695047,
      "compositeScore": -0.1745438990760765,
      "war": -0.26297004280070396,
      "dataCoverage": 0.053658536585365846,
      "confidenceFactor": 0.20012359658159343,
      "teeTimeMultiplier": null,
      "teeTimeMinutes": null,
      "notes": "âڑ ï¸ڈ Poor course fit | â†“ Off tee | âڑ ï¸ڈ Limited data (5%) | For Course Setup - خ”Predâˆ… خ”Trendâˆ…"
    },
    {
      "rank": 43,
      "dgId": "13126",
      "name": "Taylor, Nick",
      "refinedWeightedScore": -0.14481454333914773,
      "weightedScore": -0.14481454333914773,
      "compositeScore": -0.12595547042122096,
      "war": -0.08195096694605854,
      "dataCoverage": 1,
      "confidenceFactor": 1,
      "teeTimeMultiplier": null,
      "teeTimeMinutes": null,
      "notes": "âڑ ï¸ڈ Poor course fit | â†“ Off tee | For Course Setup - خ”Predâ†’ خ”Trendâ†’ | BucketSig â†“ z=-0.07 (-0.080) [Sâ†“ Mâ†“ Lâ†“ VLâ†‘]"
    },
    {
      "rank": 44,
      "dgId": "21554",
      "name": "Poston, J.T.",
      "refinedWeightedScore": -0.14026695653717824,
      "weightedScore": -0.14026695653717824,
      "compositeScore": -0.12843329207570484,
      "war": -0.10082140833226694,
      "dataCoverage": 1,
      "confidenceFactor": 1,
      "teeTimeMultiplier": null,
      "teeTimeMinutes": null,
      "notes": "â†‘ Approach | For Course Setup - خ”Predâ†’ خ”Trendâ†’ | BucketSig â†‘ z=0.44 (0.004) [Sâ†“ Mâ†‘ Lâ†“ VLâ†‘] | ًںŒ¦ï¸ڈ Weather wave: R1 AM, R2 PM (penalty=0.04)"
    },
    {
      "rank": 45,
      "dgId": "23465",
      "name": "Greyserman, Max",
      "refinedWeightedScore": -0.15857041635681723,
      "weightedScore": -0.15857041635681723,
      "compositeScore": -0.1432050165836567,
      "war": -0.10735241711294882,
      "dataCoverage": 1,
      "confidenceFactor": 1,
      "teeTimeMultiplier": null,
      "teeTimeMinutes": null,
      "notes": "âڑ ï¸ڈ Poor course fit | â„¹ï¸ڈ Recent bucket trend strong (short-term) despite baseline fit | â†‘ Around green | For Course Setup - خ”Predâ†’ خ”Trendâ†’ | BucketSig â†‘ z=0.17 (-0.040) [Sâ†“ Mâ†“ Lâ†’ VLâ†‘] | ًںŒ¦ï¸ڈ Weather wave: R1 AM, R2 PM (penalty=0.04)"
    },
    {
      "rank": 46,
      "dgId": "25569",
      "name": "Stevens, Sam",
      "refinedWeightedScore": -0.1784725571446614,
      "weightedScore": -0.1784725571446614,
      "compositeScore": -0.15401650484303647,
      "war": -0.09695238280591165,
      "dataCoverage": 1,
      "confidenceFactor": 1,
      "teeTimeMultiplier": null,
      "teeTimeMinutes": null,
      "notes": "âڑ ï¸ڈ Poor course fit | â†“ Putting | For Course Setup - خ”Predâ†’ خ”Trendâ†’ | BucketSig â†“ z=-0.78 (-0.199) [Sâ†“ Mâ†“ Lâ†“ VLâ†‘]"
    },
    {
      "rank": 47,
      "dgId": "17536",
      "name": "Spaun, J.J.",
      "refinedWeightedScore": -0.15073598100865476,
      "weightedScore": -0.15073598100865476,
      "compositeScore": -0.17030804809684802,
      "war": -0.21597620463596567,
      "dataCoverage": 1,
      "confidenceFactor": 1,
      "teeTimeMultiplier": null,
      "teeTimeMinutes": null,
      "notes": "ًں’ھ SG OTT | âڑ ï¸ڈ Poor course fit | â„¹ï¸ڈ Recent bucket trend strong (short-term) despite baseline fit | â†“ Total game | For Course Setup - خ”Predâ†’ خ”Trendâ†’ | BucketSig â†‘ z=0.66 (0.041) [Sâ†“ Mâ†‘ Lâ†‘ VLâ†‘]"
    },
    {
      "rank": 48,
      "dgId": "14704",
      "name": "Putnam, Andrew",
      "refinedWeightedScore": -0.10533368919085927,
      "weightedScore": -0.4384714934281748,
      "compositeScore": -0.4216766827531587,
      "war": -0.38248879117812135,
      "dataCoverage": 0.36910569105691055,
      "confidenceFactor": 0.24022927549362744,
      "teeTimeMultiplier": null,
      "teeTimeMinutes": null,
      "notes": "ًں’ھ SG Around Green | ًں‘چ Good course fit | â†‘ Putting | âڑ ï¸ڈ Limited data (37%) | For Course Setup - خ”Predâ†’ خ”Trendâ†’ | BucketSig â†“ z=-0.20 (-0.102) [Sâ†‘ Mâ†‘ Lâ†“ VLâ†‘] | ًںŒ¦ï¸ڈ Weather wave: R1 AM, R2 PM (penalty=0.04)"
    },
    {
      "rank": 49,
      "dgId": "13872",
      "name": "Bradley, Keegan",
      "refinedWeightedScore": -0.23586699528363073,
      "weightedScore": -0.23586699528363073,
      "compositeScore": -0.1981597032266568,
      "war": -0.11017602176038432,
      "dataCoverage": 1,
      "confidenceFactor": 1,
      "teeTimeMultiplier": null,
      "teeTimeMinutes": null,
      "notes": "ًں’ھ SG Around Green, SG T2G | ًں‘چ Good course fit | â†‘ Putting | For Course Setup - خ”Predâ†’ خ”Trendâ†“ | BucketSig â†“ z=-0.77 (-0.197) [Sâ†“ Mâ†“ Lâ†“ VLâ†‘]"
    },
    {
      "rank": 50,
      "dgId": "14578",
      "name": "Henley, Russell",
      "refinedWeightedScore": -0.2565419833105697,
      "weightedScore": -0.2565419833105697,
      "compositeScore": -0.2254521773442954,
      "war": -0.15290929675632206,
      "dataCoverage": 0.936910569105691,
      "confidenceFactor": 1,
      "teeTimeMultiplier": null,
      "teeTimeMinutes": null,
      "notes": "âڑ ï¸ڈ Poor course fit | â†“ Around green | For Course Setup - خ”Predâ†’ خ”Trendâ†’ | BucketSig â†“ z=-0.31 (-0.120) [Sâ†“ Mâ†“ Lâ†“ VLâ†‘] | ًںŒ¦ï¸ڈ Weather wave: R1 AM, R2 PM (penalty=0.04)"
    },
    {
      "rank": 51,
      "dgId": "26096",
      "name": "Bhatia, Akshay",
      "refinedWeightedScore": -0.23203344075103818,
      "weightedScore": -0.23203344075103818,
      "compositeScore": -0.2256885938827342,
      "war": -0.21088395119002495,
      "dataCoverage": 1,
      "confidenceFactor": 1,
      "teeTimeMultiplier": null,
      "teeTimeMinutes": null,
      "notes": "âڑ ï¸ڈ Poor course fit | â„¹ï¸ڈ Recent bucket trend strong (short-term) despite baseline fit | â†‘ Putting | For Course Setup - خ”Predâ†’ خ”Trendâ†’ | BucketSig â†‘ z=0.30 (-0.018) [Sâ†“ Mâ†‘ Lâ†‘ VLâ†“] | ًںŒ¦ï¸ڈ Weather wave: R1 AM, R2 PM (penalty=0.04)"
    },
    {
      "rank": 52,
      "dgId": "27194",
      "name": "Hall, Harry",
      "refinedWeightedScore": -0.27764051460652006,
      "weightedScore": -0.27764051460652006,
      "compositeScore": -0.23149202842354893,
      "war": -0.1238122273299497,
      "dataCoverage": 1,
      "confidenceFactor": 1,
      "teeTimeMultiplier": null,
      "teeTimeMinutes": null,
      "notes": "ًں’ھ SG Around Green | ًں‘چ Good course fit | â†‘ Off tee | For Course Setup - خ”Predâ†’ خ”Trendâ†’ | BucketSig â†“ z=-0.49 (-0.150) [Sâ†“ Mâ†“ Lâ†“ VLâ†‘] | ًںŒ¦ï¸ڈ Weather wave: R1 AM, R2 PM (penalty=0.04)"
    },
    {
      "rank": 53,
      "dgId": "28635",
      "name": "McCarty, Matt",
      "refinedWeightedScore": -0.2526350955836625,
      "weightedScore": -0.2526350955836625,
      "compositeScore": -0.23191005190294595,
      "war": -0.18355161664794076,
      "dataCoverage": 1,
      "confidenceFactor": 1,
      "teeTimeMultiplier": null,
      "teeTimeMinutes": null,
      "notes": "âڑ ï¸ڈ Poor course fit | â„¹ï¸ڈ Recent bucket trend strong (short-term) despite baseline fit | â†“ Approach | For Course Setup - خ”Predâ†’ خ”Trendâ†’ | BucketSig â†‘ z=0.23 (-0.031) [Sâ†“ Mâ†“ Lâ†“ VLâ†‘] | ًںŒ¦ï¸ڈ Weather wave: R1 AM, R2 PM (penalty=0.04)"
    },
    {
      "rank": 54,
      "dgId": "17511",
      "name": "Straka, Sepp",
      "refinedWeightedScore": -0.2771339696541672,
      "weightedScore": -0.2771339696541672,
      "compositeScore": -0.23268586169403144,
      "war": -0.12897360978704794,
      "dataCoverage": 1,
      "confidenceFactor": 1,
      "teeTimeMultiplier": null,
      "teeTimeMinutes": null,
      "notes": "ًں’ھ Approach <100 GIR | âڑ ï¸ڈ Poor course fit | â†“ Off tee | For Course Setup - خ”Predâ†’ خ”Trendâ†’ | BucketSig â†“ z=-0.09 (-0.084) [Sâ†“ Mâ†“ Lâ†“ VLâ†‘] | ًںŒ¦ï¸ڈ Weather wave: R1 AM, R2 PM (penalty=0.04)"
    },
    {
      "rank": 55,
      "dgId": "23323",
      "name": "MacIntyre, Robert",
      "refinedWeightedScore": -0.2901348776932018,
      "weightedScore": -0.2901348776932018,
      "compositeScore": -0.2459383369948231,
      "war": -0.14281307536527285,
      "dataCoverage": 1,
      "confidenceFactor": 1,
      "teeTimeMultiplier": null,
      "teeTimeMinutes": null,
      "notes": "ًں’ھ SG Putting | ًں‘چ Good course fit | â†‘ Around green | For Course Setup - خ”Predâ†’ خ”Trendâ†’ | BucketSig â†“ z=-0.03 (-0.075) [Sâ†‘ Mâ†“ Lâ†“ VLâ†“] | ًںŒ¦ï¸ڈ Weather wave: R1 AM, R2 PM (penalty=0.04)"
    },
    {
      "rank": 56,
      "dgId": "19870",
      "name": "McCarthy, Denny",
      "refinedWeightedScore": -0.3084475931907842,
      "weightedScore": -0.3084475931907842,
      "compositeScore": -0.258926157352785,
      "war": -0.14337614039745358,
      "dataCoverage": 1,
      "confidenceFactor": 1,
      "teeTimeMultiplier": null,
      "teeTimeMinutes": null,
      "notes": "â†‘ Total game | For Course Setup - خ”Predâ†’ خ”Trendâ†’ | BucketSig â†“ z=-0.65 (-0.178) [Sâ†“ Mâ†“ Lâ†“ VLâ†‘]"
    },
    {
      "rank": 57,
      "dgId": "22760",
      "name": "Hisatsune, Ryo",
      "refinedWeightedScore": -0.30254683820650596,
      "weightedScore": -0.30254683820650596,
      "compositeScore": -0.2631056052469244,
      "war": -0.17107606167456743,
      "dataCoverage": 1,
      "confidenceFactor": 1,
      "teeTimeMultiplier": null,
      "teeTimeMinutes": null,
      "notes": "âڑ ï¸ڈ Poor course fit | â†‘ Putting | For Course Setup - خ”Predâ†’ خ”Trendâ†’ | BucketSig â†“ z=-0.19 (-0.101) [Sâ†“ Mâ†“ Lâ†“ VLâ†‘]"
    },
    {
      "rank": 58,
      "dgId": "23475",
      "name": "Novak, Andrew",
      "refinedWeightedScore": -0.3141059374050066,
      "weightedScore": -0.3141059374050066,
      "compositeScore": -0.277321724517683,
      "war": -0.1914918944472613,
      "dataCoverage": 1,
      "confidenceFactor": 1,
      "teeTimeMultiplier": null,
      "teeTimeMinutes": null,
      "notes": "âڑ ï¸ڈ Poor course fit | â†‘ Approach | For Course Setup - خ”Predâ†’ خ”Trendâ†’ | BucketSig â†“ z=-0.05 (-0.077) [Sâ†“ Mâ†“ Lâ†“ VLâ†‘] | ًںŒ¦ï¸ڈ Weather wave: R1 AM, R2 PM (penalty=0.04)"
    },
    {
      "rank": 59,
      "dgId": "9771",
      "name": "Day, Jason",
      "refinedWeightedScore": -0.3237782529918727,
      "weightedScore": -0.3237782529918727,
      "compositeScore": -0.2784618357260651,
      "war": -0.17272352877251404,
      "dataCoverage": 0.936910569105691,
      "confidenceFactor": 1,
      "teeTimeMultiplier": null,
      "teeTimeMinutes": null,
      "notes": "ًں’ھ SG Around Green | ًں‘چ Good course fit | â†“ Tee-to-green | For Course Setup - خ”Predâ†’ خ”Trendâ†’ | BucketSig â†“ z=-0.42 (-0.140) [Sâ†‘ Mâ†“ Lâ†“ VLâ†“]"
    },
    {
      "rank": 60,
      "dgId": "16283",
      "name": "Rodgers, Patrick",
      "refinedWeightedScore": -0.32971343260759156,
      "weightedScore": -0.32971343260759156,
      "compositeScore": -0.285073930413121,
      "war": -0.1809150919593564,
      "dataCoverage": 1,
      "confidenceFactor": 1,
      "teeTimeMultiplier": null,
      "teeTimeMinutes": null,
      "notes": "âڑ ï¸ڈ Poor course fit | â†‘ Off tee | For Course Setup - خ”Predâ†’ خ”Trendâ†’ | BucketSig â†“ z=-0.20 (-0.103) [Sâ†“ Mâ†“ Lâ†“ VLâ†‘] | ًںŒ¦ï¸ڈ Weather wave: R1 AM, R2 PM (penalty=0.04)"
    },
    {
      "rank": 61,
      "dgId": "7399",
      "name": "Glover, Lucas",
      "refinedWeightedScore": -0.35649283815067334,
      "weightedScore": -0.35649283815067334,
      "compositeScore": -0.31658713529834936,
      "war": -0.22347382864292686,
      "dataCoverage": 0.8422764227642277,
      "confidenceFactor": 1,
      "teeTimeMultiplier": null,
      "teeTimeMinutes": null,
      "notes": "â†“ Around green | For Course Setup - خ”Predâ†“ خ”Trendâ†“ | BucketSig â†“ z=-2.13 (-0.423) [Sâ†“ Mâ†“ Lâ†“ VLâ†‘]"
    },
    {
      "rank": 62,
      "dgId": "12423",
      "name": "Kirk, Chris",
      "refinedWeightedScore": -0.40801229616285806,
      "weightedScore": -0.40801229616285806,
      "compositeScore": -0.3548311168810474,
      "war": -0.23074169855682258,
      "dataCoverage": 1,
      "confidenceFactor": 1,
      "teeTimeMultiplier": null,
      "teeTimeMinutes": null,
      "notes": "ًں’ھ Approach <100 GIR | âڑ ï¸ڈ Poor course fit | â†‘ Putting | For Course Setup - خ”Predâ†’ خ”Trendâ†“ | BucketSig â†“ z=-0.45 (-0.143) [Sâ†‘ Mâ†“ Lâ†“ VLâ†‘]"
    },
    {
      "rank": 63,
      "dgId": "17543",
      "name": "Kim, Michael",
      "refinedWeightedScore": -0.4531950372144385,
      "weightedScore": -0.4531950372144385,
      "compositeScore": -0.4012261299979157,
      "war": -0.27996534649269583,
      "dataCoverage": 1,
      "confidenceFactor": 1,
      "teeTimeMultiplier": null,
      "teeTimeMinutes": null,
      "notes": "ًں’ھ SG Around Green, Approach <100 GIR | ًں‘چ Good course fit | â†“ Around green | For Course Setup - خ”Predâ†’ خ”Trendâ†’ | BucketSig â†‘ z=0.05 (-0.061) [Sâ†“ Mâ†“ Lâ†“ VLâ†‘]"
    },
    {
      "rank": 64,
      "dgId": "26649",
      "name": "Thorbjornsen, Michael",
      "refinedWeightedScore": -0.44030180320087964,
      "weightedScore": -0.44030180320087964,
      "compositeScore": -0.4024790018938534,
      "war": -0.3142257988441255,
      "dataCoverage": 1,
      "confidenceFactor": 1,
      "teeTimeMultiplier": null,
      "teeTimeMinutes": null,
      "notes": "ًں’ھ SG OTT | âڑ ï¸ڈ Poor course fit | â„¹ï¸ڈ Recent bucket trend strong (short-term) despite baseline fit | â†“ Total game | For Course Setup - خ”Predâ†’ خ”Trendâ†’ | BucketSig â†‘ z=0.13 (-0.047) [Sâ†‘ Mâ†“ Lâ†‘ VLâ†“] | ًںŒ¦ï¸ڈ Weather wave: R1 AM, R2 PM (penalty=0.04)"
    },
    {
      "rank": 65,
      "dgId": "23014",
      "name": "Theegala, Sahith",
      "refinedWeightedScore": -0.4936475578317529,
      "weightedScore": -0.4936475578317529,
      "compositeScore": -0.4509949692077031,
      "war": -0.35147226241825374,
      "dataCoverage": 1,
      "confidenceFactor": 1,
      "teeTimeMultiplier": null,
      "teeTimeMinutes": null,
      "notes": "âڑ ï¸ڈ Poor course fit | â†“ Around green | For Course Setup - خ”Predâ†’ خ”Trendâ†’ | BucketSig â†“ z=-0.07 (-0.081) [Sâ†“ Mâ†“ Lâ†“ VLâ†‘]"
    },
    {
      "rank": 66,
      "dgId": "15575",
      "name": "Hoge, Tom",
      "refinedWeightedScore": -0.5308953977410872,
      "weightedScore": -0.5308953977410872,
      "compositeScore": -0.46261796115020126,
      "war": -0.3033039424381341,
      "dataCoverage": 1,
      "confidenceFactor": 1,
      "teeTimeMultiplier": null,
      "teeTimeMinutes": null,
      "notes": "ًں’ھ SG Around Green | ًں‘چ Good course fit | â†“ Total game | For Course Setup - خ”Predâ†’ خ”Trendâ†’ | BucketSig â†“ z=-0.45 (-0.144) [Sâ†“ Mâ†“ Lâ†“ VLâ†‘] | ًںŒ¦ï¸ڈ Weather wave: R1 AM, R2 PM (penalty=0.04)"
    },
    {
      "rank": 67,
      "dgId": "11276",
      "name": "Horschel, Billy",
      "refinedWeightedScore": -0.5203382302967741,
      "weightedScore": -0.5203382302967741,
      "compositeScore": -0.4725997531755168,
      "war": -0.36120997322591647,
      "dataCoverage": 1,
      "confidenceFactor": 1,
      "teeTimeMultiplier": null,
      "teeTimeMinutes": null,
      "notes": "âڑ ï¸ڈ Poor course fit | â†“ Approach | For Course Setup - خ”Predâ†“ خ”Trendâ†“ | BucketSig â†“ z=-0.99 (-0.234) [Sâ†“ Mâ†“ Lâ†“ VLâ†‘] | ًںŒ¦ï¸ڈ Weather wave: R1 AM, R2 PM (penalty=0.04)"
    },
    {
      "rank": 68,
      "dgId": "13508",
      "name": "Vegas, Jhonattan",
      "refinedWeightedScore": -0.5606118818916839,
      "weightedScore": -0.5606118818916839,
      "compositeScore": -0.5105628587831472,
      "war": -0.3937818048632284,
      "dataCoverage": 1,
      "confidenceFactor": 1,
      "teeTimeMultiplier": null,
      "teeTimeMinutes": null,
      "notes": "âڑ ï¸ڈ Poor course fit | â†‘ Off tee | For Course Setup - خ”Predâ†“ خ”Trendâ†’ | BucketSig â†“ z=-0.77 (-0.197) [Sâ†“ Mâ†“ Lâ†“ VLâ†“] | ًںŒ¦ï¸ڈ Weather wave: R1 AM, R2 PM (penalty=0.04)"
    },
    {
      "rank": 69,
      "dgId": "8825",
      "name": "Harman, Brian",
      "refinedWeightedScore": -0.6262764405753243,
      "weightedScore": -0.6262764405753243,
      "compositeScore": -0.5772675265988186,
      "war": -0.4629133939869723,
      "dataCoverage": 0.936910569105691,
      "confidenceFactor": 1,
      "teeTimeMultiplier": null,
      "teeTimeMinutes": null,
      "notes": "âڑ ï¸ڈ Poor course fit | â†‘ Around green | For Course Setup - خ”Predâ†’ خ”Trendâ†’ | BucketSig â†“ z=-0.49 (-0.150) [Sâ†“ Mâ†‘ Lâ†“ VLâ†“] | ًںŒ¦ï¸ڈ Weather wave: R1 AM, R2 PM (penalty=0.04)"
    },
    {
      "rank": 70,
      "dgId": "14502",
      "name": "Cauley, Bud",
      "refinedWeightedScore": -0.6423499070460035,
      "weightedScore": -0.6423499070460035,
      "compositeScore": -0.5809080103825346,
      "war": -0.4375435848344407,
      "dataCoverage": 1,
      "confidenceFactor": 1,
      "teeTimeMultiplier": null,
      "teeTimeMinutes": null,
      "notes": "âڑ ï¸ڈ Poor course fit | â†‘ Tee-to-green | For Course Setup - خ”Predâ†’ خ”Trendâ†’ | BucketSig â†“ z=-0.26 (-0.112) [Sâ†“ Mâ†“ Lâ†“ VLâ†‘]"
    },
    {
      "rank": 71,
      "dgId": "18628",
      "name": "Campbell, Brian",
      "refinedWeightedScore": -0.9537220555935507,
      "weightedScore": -0.9537220555935507,
      "compositeScore": -0.8531274158585951,
      "war": -0.6184065898103654,
      "dataCoverage": 1,
      "confidenceFactor": 1,
      "teeTimeMultiplier": null,
      "teeTimeMinutes": null,
      "notes": "â†“ Below field average | âڑ ï¸ڈ Poor course fit | â†“ Putting | For Course Setup - خ”Predâ†’ خ”Trendâ†’ | BucketSig â†“ z=-0.53 (-0.157) [Sâ†“ Mâ†“ Lâ†“ VLâ†“] | ًںŒ¦ï¸ڈ Weather wave: R1 AM, R2 PM (penalty=0.04)"
    },
    {
      "rank": 72,
      "dgId": "6093",
      "name": "Rose, Justin",
      "refinedWeightedScore": -1.0323541033605517,
      "weightedScore": -1.0323541033605517,
      "compositeScore": -0.8705355240533281,
      "war": -0.49295883900314014,
      "dataCoverage": 1,
      "confidenceFactor": 1,
      "teeTimeMultiplier": null,
      "teeTimeMinutes": null,
      "notes": "ًں’ھ Approach <100 GIR | âڑ ï¸ڈ Poor course fit | â†‘ Putting | For Course Setup - خ”Predâ†’ خ”Trendâ†’ | BucketSig â†“ z=-0.53 (-0.157) [Sâ†“ Mâ†“ Lâ†“ VLâ†“] | ًںŒ¦ï¸ڈ Weather wave: R1 AM, R2 PM (penalty=0.04)"
    }
  ]
}