{
  "book": "draftkings",
  "event_completed": "2026-02-08",
  "event_id": "3",
  "event_name": "WM Phoenix Open",
  "market": "win",
  "odds": [
    {
      "bet_outcome_numeric": 0,
      "bet_outcome_text": "loss",
      "close_odds": 3.3,
      "close_time": "2026-02-05 07:45",
      "dg_id": 18417,
      "open_odds": 3.1,
      "open_time": "2026-02-02 14:00",
      "outcome": "T3",
      "player_name": "Scheffler, Scottie"
    },
    {
      "bet_outcome_numeric": 0,
      "bet_outcome_text": "loss",
      "close_odds": 20.5,
      "close_time": "2026-02-05 07:45",
      "dg_id": 19895,
      "open_odds": 21,
      "open_time": "2026-02-02 14:00",
      "outcome": "T41",
      "player_name": "Schauffele, Xander"
    },
    {
      "bet_outcome_numeric": 0,
      "bet_outcome_text": "loss",
      "close_odds": 26,
      "close_time": "2026-02-05 07:45",
      "dg_id": 26651,
      "open_odds": 28,
      "open_time": "2026-02-02 14:00",
      "outcome": "T41",
      "player_name": "Young, Cameron"
    },
    {
      "bet_outcome_numeric": 0,
      "bet_outcome_text": "loss",
      "close_odds": 27,
      "close_time": "2026-02-05 07:45",
      "dg_id": 13562,
      "open_odds": 28,
      "open_time": "2026-02-02 14:00",
      "outcome": "2",
      "player_name": "Matsuyama, Hideki"
    },
    {
      "bet_outcome_numeric": 0,
      "bet_outcome_text": "loss",
      "close_odds": 30,
      "close_time": "2026-02-05 07:45",
      "dg_id": 14609,
      "open_odds": 31,
      "open_time": "2026-02-02 14:00",
      "outcome": "T3",
      "player_name": "Kim, Si Woo"
    },
    {
      "bet_outcome_numeric": 0,
      "bet_outcome_text": "loss",
      "close_odds": 32,
      "close_time": "2026-02-05 07:45",
      "dg_id": 24968,
      "open_odds": 28,
      "open_time": "2026-02-02 14:00",
      "outcome": "T28",
      "player_name": "Griffin, Ben"
    },
    {
      "bet_outcome_numeric": 0,
      "bet_outcome_text": "loss",
      "close_odds": 34,
      "close_time": "2026-02-05 07:45",
      "dg_id": 19483,
      "open_odds": 28,
      "open_time": "2026-02-02 14:00",
      "outcome": "CUT",
      "player_name": "Burns, Sam"
    },
    {
      "bet_outcome_numeric": 0,
      "bet_outcome_text": "loss",
      "close_odds": 34,
      "close_time": "2026-02-05 07:45",
      "dg_id": 16243,
      "open_odds": 39,
      "open_time": "2026-02-02 14:00",
      "outcome": "CUT",
      "player_name": "Koepka, Brooks"
    },
    {
      "bet_outcome_numeric": 0,
      "bet_outcome_text": "loss",
      "close_odds": 36,
      "close_time": "2026-02-05 07:45",
      "dg_id": 18634,
      "open_odds": 37,
      "open_time": "2026-02-02 14:00",
      "outcome": "T13",
      "player_name": "McNealy, Maverick"
    },
    {
      "bet_outcome_numeric": 1,
      "bet_outcome_text": "paid in full",
      "close_odds": 39,
      "close_time": "2026-02-05 07:45",
      "dg_id": 27774,
      "open_odds": 45,
      "open_time": "2026-02-02 14:00",
      "outcome": "1",
      "player_name": "Gotterup, Chris"
    },
    {
      "bet_outcome_numeric": 0,
      "bet_outcome_text": "loss",
      "close_odds": 39,
      "close_time": "2026-02-05 07:45",
      "dg_id": 18841,
      "open_odds": 35,
      "open_time": "2026-02-02 14:00",
      "outcome": "T10",
      "player_name": "Hovland, Viktor"
    },
    {
      "bet_outcome_numeric": 0,
      "bet_outcome_text": "loss",
      "close_odds": 42,
      "close_time": "2026-02-05 07:45",
      "dg_id": 12965,
      "open_odds": 40,
      "open_time": "2026-02-02 14:00",
      "outcome": "T18",
      "player_name": "Fowler, Rickie"
    },
    {
      "bet_outcome_numeric": 0,
      "bet_outcome_text": "loss",
      "close_odds": 43,
      "close_time": "2026-02-05 07:45",
      "dg_id": 14577,
      "open_odds": 45,
      "open_time": "2026-02-02 14:00",
      "outcome": "T28",
      "player_name": "English, Harris"
    },
    {
      "bet_outcome_numeric": 0,
      "bet_outcome_text": "loss",
      "close_odds": 47,
      "close_time": "2026-02-05 07:45",
      "dg_id": 19396,
      "open_odds": 49,
      "open_time": "2026-02-02 14:00",
      "outcome": "8",
      "player_name": "Knapp, Jake"
    },
    {
      "bet_outcome_numeric": 0,
      "bet_outcome_text": "loss",
      "close_odds": 49,
      "close_time": "2026-02-05 07:45",
      "dg_id": 23014,
      "open_odds": 51,
      "open_time": "2026-02-02 14:00",
      "outcome": "T18",
      "player_name": "Theegala, Sahith"
    },
    {
      "bet_outcome_numeric": 0,
      "bet_outcome_text": "loss",
      "close_odds": 50,
      "close_time": "2026-02-05 07:45",
      "dg_id": 22085,
      "open_odds": 45,
      "open_time": "2026-02-02 14:00",
      "outcome": "T54",
      "player_name": "Morikawa, Collin"
    },
    {
      "bet_outcome_numeric": 0,
      "bet_outcome_text": "loss",
      "close_odds": 52,
      "close_time": "2026-02-05 07:45",
      "dg_id": 17646,
      "open_odds": 45,
      "open_time": "2026-02-02 14:00",
      "outcome": "9",
      "player_name": "Fitzpatrick, Matt"
    },
    {
      "bet_outcome_numeric": 0,
      "bet_outcome_text": "loss",
      "close_odds": 56,
      "close_time": "2026-02-05 07:45",
      "dg_id": 27194,
      "open_odds": 48,
      "open_time": "2026-02-02 14:00",
      "outcome": "CUT",
      "player_name": "Hall, Harry"
    },
    {
      "bet_outcome_numeric": 0,
      "bet_outcome_text": "loss",
      "close_odds": 58,
      "close_time": "2026-02-05 07:45",
      "dg_id": 28309,
      "open_odds": 61,
      "open_time": "2026-02-02 14:00",
      "outcome": "T10",
      "player_name": "Coody, Pierceson"
    },
    {
      "bet_outcome_numeric": 0,
      "bet_outcome_text": "loss",
      "close_odds": 59,
      "close_time": "2026-02-05 07:45",
      "dg_id": 23838,
      "open_odds": 65,
      "open_time": "2026-02-02 14:00",
      "outcome": "T24",
      "player_name": "Hojgaard, Rasmus"
    },
    {
      "bet_outcome_numeric": 0,
      "bet_outcome_text": "loss",
      "close_odds": 59,
      "close_time": "2026-02-05 07:45",
      "dg_id": 14636,
      "open_odds": 51,
      "open_time": "2026-02-02 14:00",
      "outcome": "CUT",
      "player_name": "Spieth, Jordan"
    },
    {
      "bet_outcome_numeric": 0,
      "bet_outcome_text": "loss",
      "close_odds": 60,
      "close_time": "2026-02-05 07:45",
      "dg_id": 26649,
      "open_odds": 59,
      "open_time": "2026-02-02 14:00",
      "outcome": "T3",
      "player_name": "Thorbjornsen, Michael"
    },
    {
      "bet_outcome_numeric": 0,
      "bet_outcome_text": "loss",
      "close_odds": 65,
      "close_time": "2026-02-05 07:45",
      "dg_id": 17365,
      "open_odds": 65,
      "open_time": "2026-02-02 14:00",
      "outcome": "T41",
      "player_name": "Mitchell, Keith"
    },
    {
      "bet_outcome_numeric": 0,
      "bet_outcome_text": "loss",
      "close_odds": 66,
      "close_time": "2026-02-05 07:45",
      "dg_id": 17606,
      "open_odds": 68,
      "open_time": "2026-02-02 14:00",
      "outcome": "T16",
      "player_name": "Berger, Daniel"
    },
    {
      "bet_outcome_numeric": 0,
      "bet_outcome_text": "loss",
      "close_odds": 67,
      "close_time": "2026-02-05 07:45",
      "dg_id": 21891,
      "open_odds": 60,
      "open_time": "2026-02-02 14:00",
      "outcome": "T24",
      "player_name": "Kitayama, Kurt"
    },
    {
      "bet_outcome_numeric": 0,
      "bet_outcome_text": "loss",
      "close_odds": 73,
      "close_time": "2026-02-05 07:45",
      "dg_id": 23604,
      "open_odds": 63,
      "open_time": "2026-02-02 14:00",
      "outcome": "T35",
      "player_name": "Clark, Wyndham"
    },
    {
      "bet_outcome_numeric": 0,
      "bet_outcome_text": "loss",
      "close_odds": 73,
      "close_time": "2026-02-05 07:45",
      "dg_id": 23602,
      "open_odds": 77,
      "open_time": "2026-02-02 14:00",
      "outcome": "T3",
      "player_name": "Hojgaard, Nicolai"
    },
    {
      "bet_outcome_numeric": 0,
      "bet_outcome_text": "loss",
      "close_odds": 73,
      "close_time": "2026-02-05 07:45",
      "dg_id": 17576,
      "open_odds": 58,
      "open_time": "2026-02-02 14:00",
      "outcome": "CUT",
      "player_name": "Conners, Corey"
    },
    {
      "bet_outcome_numeric": 0,
      "bet_outcome_text": "loss",
      "close_odds": 75,
      "close_time": "2026-02-05 07:45",
      "dg_id": 28635,
      "open_odds": 77,
      "open_time": "2026-02-02 14:00",
      "outcome": "CUT",
      "player_name": "McCarty, Matt"
    },
    {
      "bet_outcome_numeric": 0,
      "bet_outcome_text": "loss",
      "close_odds": 75,
      "close_time": "2026-02-05 07:45",
      "dg_id": 16841,
      "open_odds": 71,
      "open_time": "2026-02-02 14:00",
      "outcome": "T28",
      "player_name": "Lee, Min Woo"
    },
    {
      "bet_outcome_numeric": 0,
      "bet_outcome_text": "loss",
      "close_odds": 79,
      "close_time": "2026-02-05 07:45",
      "dg_id": 21554,
      "open_odds": 73,
      "open_time": "2026-02-02 14:00",
      "outcome": "T35",
      "player_name": "Poston, J.T."
    },
    {
      "bet_outcome_numeric": 0,
      "bet_outcome_text": "loss",
      "close_odds": 83,
      "close_time": "2026-02-05 07:45",
      "dg_id": 25569,
      "open_odds": 87,
      "open_time": "2026-02-02 14:00",
      "outcome": "T35",
      "player_name": "Stevens, Sam"
    },
    {
      "bet_outcome_numeric": 0,
      "bet_outcome_text": "loss",
      "close_odds": 85,
      "close_time": "2026-02-05 07:45",
      "dg_id": 13126,
      "open_odds": 71,
      "open_time": "2026-02-02 14:00",
      "outcome": "T28",
      "player_name": "Taylor, Nick"
    },
    {
      "bet_outcome_numeric": 0,
      "bet_outcome_text": "loss",
      "close_odds": 85,
      "close_time": "2026-02-05 07:45",
      "dg_id": 24342,
      "open_odds": 89,
      "open_time": "2026-02-02 14:00",
      "outcome": "CUT",
      "player_name": "Higgo, Garrick"
    },
    {
      "bet_outcome_numeric": 0,
      "bet_outcome_text": "loss",
      "close_odds": 87,
      "close_time": "2026-02-05 07:45",
      "dg_id": 17511,
      "open_odds": 79,
      "open_time": "2026-02-02 14:00",
      "outcome": "T18",
      "player_name": "Straka, Sepp"
    },
    {
      "bet_outcome_numeric": 0,
      "bet_outcome_text": "loss",
      "close_odds": 91,
      "close_time": "2026-02-05 07:45",
      "dg_id": 27364,
      "open_odds": 93,
      "open_time": "2026-02-02 14:00",
      "outcome": "T64",
      "player_name": "Thompson, Davis"
    },
    {
      "bet_outcome_numeric": 0,
      "bet_outcome_text": "loss",
      "close_odds": 93,
      "close_time": "2026-02-05 07:45",
      "dg_id": 15310,
      "open_odds": 95,
      "open_time": "2026-02-02 14:00",
      "outcome": "CUT",
      "player_name": "Li, Haotong"
    },
    {
      "bet_outcome_numeric": 0,
      "bet_outcome_text": "loss",
      "close_odds": 97,
      "close_time": "2026-02-05 07:45",
      "dg_id": 13412,
      "open_odds": 87,
      "open_time": "2026-02-02 14:00",
      "outcome": "CUT",
      "player_name": "Olesen, Thorbjorn"
    },
    {
      "bet_outcome_numeric": 0,
      "bet_outcome_text": "loss",
      "close_odds": 97,
      "close_time": "2026-02-05 07:45",
      "dg_id": 18103,
      "open_odds": 91,
      "open_time": "2026-02-02 14:00",
      "outcome": "CUT",
      "player_name": "Bezuidenhout, Christiaan"
    },
    {
      "bet_outcome_numeric": 0,
      "bet_outcome_text": "loss",
      "close_odds": 106,
      "close_time": "2026-02-05 07:45",
      "dg_id": 23475,
      "open_odds": 106,
      "open_time": "2026-02-02 14:00",
      "outcome": "CUT",
      "player_name": "Novak, Andrew"
    },
    {
      "bet_outcome_numeric": 0,
      "bet_outcome_text": "loss",
      "close_odds": 106,
      "close_time": "2026-02-05 07:45",
      "dg_id": 23841,
      "open_odds": 106,
      "open_time": "2026-02-02 14:00",
      "outcome": "T41",
      "player_name": "Neergaard-Petersen, Rasmus"
    },
    {
      "bet_outcome_numeric": 0,
      "bet_outcome_text": "loss",
      "close_odds": 111,
      "close_time": "2026-02-05 07:45",
      "dg_id": 23504,
      "open_odds": 101,
      "open_time": "2026-02-02 14:00",
      "outcome": "T24",
      "player_name": "Hoey, Rico"
    },
    {
      "bet_outcome_numeric": 0,
      "bet_outcome_text": "loss",
      "close_odds": 111,
      "close_time": "2026-02-05 07:45",
      "dg_id": 23465,
      "open_odds": 111,
      "open_time": "2026-02-02 14:00",
      "outcome": "CUT",
      "player_name": "Greyserman, Max"
    },
    {
      "bet_outcome_numeric": 0,
      "bet_outcome_text": "loss",
      "close_odds": 116,
      "close_time": "2026-02-05 07:45",
      "dg_id": 16283,
      "open_odds": 121,
      "open_time": "2026-02-02 14:00",
      "outcome": "T60",
      "player_name": "Rodgers, Patrick"
    },
    {
      "bet_outcome_numeric": 0,
      "bet_outcome_text": "loss",
      "close_odds": 121,
      "close_time": "2026-02-05 07:45",
      "dg_id": 17538,
      "open_odds": 121,
      "open_time": "2026-02-02 14:00",
      "outcome": "T66",
      "player_name": "Homa, Max"
    },
    {
      "bet_outcome_numeric": 0,
      "bet_outcome_text": "loss",
      "close_odds": 131,
      "close_time": "2026-02-05 07:45",
      "dg_id": 22465,
      "open_odds": 121,
      "open_time": "2026-02-02 14:00",
      "outcome": "CUT",
      "player_name": "Penge, Marco"
    },
    {
      "bet_outcome_numeric": 0,
      "bet_outcome_text": "loss",
      "close_odds": 131,
      "close_time": "2026-02-05 07:45",
      "dg_id": 29433,
      "open_odds": 121,
      "open_time": "2026-02-02 14:00",
      "outcome": "T18",
      "player_name": "Bridgeman, Jacob"
    },
    {
      "bet_outcome_numeric": 0,
      "bet_outcome_text": "loss",
      "close_odds": 131,
      "close_time": "2026-02-05 07:45",
      "dg_id": 23505,
      "open_odds": 116,
      "open_time": "2026-02-02 14:00",
      "outcome": "T48",
      "player_name": "McGreevy, Max"
    },
    {
      "bet_outcome_numeric": 0,
      "bet_outcome_text": "loss",
      "close_odds": 141,
      "close_time": "2026-02-05 07:45",
      "dg_id": 32457,
      "open_odds": 161,
      "open_time": "2026-02-02 14:00",
      "outcome": "T41",
      "player_name": "Keefer, Johnny"
    },
    {
      "bet_outcome_numeric": 0,
      "bet_outcome_text": "loss",
      "close_odds": 146,
      "close_time": "2026-02-05 07:45",
      "dg_id": 26096,
      "open_odds": 141,
      "open_time": "2026-02-02 14:00",
      "outcome": "T3",
      "player_name": "Bhatia, Akshay"
    },
    {
      "bet_outcome_numeric": 0,
      "bet_outcome_text": "loss",
      "close_odds": 146,
      "close_time": "2026-02-05 07:45",
      "dg_id": 11676,
      "open_odds": 161,
      "open_time": "2026-02-02 14:00",
      "outcome": "CUT",
      "player_name": "Finau, Tony"
    },
    {
      "bet_outcome_numeric": 0,
      "bet_outcome_text": "loss",
      "close_odds": 146,
      "close_time": "2026-02-05 07:45",
      "dg_id": 28159,
      "open_odds": 146,
      "open_time": "2026-02-02 14:00",
      "outcome": "T18",
      "player_name": "Meissner, Mac"
    },
    {
      "bet_outcome_numeric": 0,
      "bet_outcome_text": "loss",
      "close_odds": 146,
      "close_time": "2026-02-05 07:45",
      "dg_id": 21407,
      "open_odds": 141,
      "open_time": "2026-02-02 14:00",
      "outcome": "T41",
      "player_name": "Reitan, Kristoffer"
    },
    {
      "bet_outcome_numeric": 0,
      "bet_outcome_text": "loss",
      "close_odds": 151,
      "close_time": "2026-02-05 07:45",
      "dg_id": 17543,
      "open_odds": 111,
      "open_time": "2026-02-02 14:00",
      "outcome": "T18",
      "player_name": "Kim, Michael"
    },
    {
      "bet_outcome_numeric": 0,
      "bet_outcome_text": "loss",
      "close_odds": 156,
      "close_time": "2026-02-05 07:45",
      "dg_id": 22760,
      "open_odds": 161,
      "open_time": "2026-02-02 14:00",
      "outcome": "T10",
      "player_name": "Hisatsune, Ryo"
    },
    {
      "bet_outcome_numeric": 0,
      "bet_outcome_text": "loss",
      "close_odds": 156,
      "close_time": "2026-02-05 07:45",
      "dg_id": 14502,
      "open_odds": 141,
      "open_time": "2026-02-02 14:00",
      "outcome": "T68",
      "player_name": "Cauley, Bud"
    },
    {
      "bet_outcome_numeric": 0,
      "bet_outcome_text": "loss",
      "close_odds": 156,
      "close_time": "2026-02-05 07:45",
      "dg_id": 16394,
      "open_odds": 141,
      "open_time": "2026-02-02 14:00",
      "outcome": "T28",
      "player_name": "Jaeger, Stephan"
    },
    {
      "bet_outcome_numeric": 0,
      "bet_outcome_text": "loss",
      "close_odds": 161,
      "close_time": "2026-02-05 07:45",
      "dg_id": 21756,
      "open_odds": 156,
      "open_time": "2026-02-02 14:00",
      "outcome": "CUT",
      "player_name": "Cole, Eric"
    },
    {
      "bet_outcome_numeric": 0,
      "bet_outcome_text": "loss",
      "close_odds": 171,
      "close_time": "2026-02-05 07:45",
      "dg_id": 18474,
      "open_odds": 161,
      "open_time": "2026-02-02 14:00",
      "outcome": "T35",
      "player_name": "Smalley, Alex"
    },
    {
      "bet_outcome_numeric": 0,
      "bet_outcome_text": "loss",
      "close_odds": 181,
      "close_time": "2026-02-05 07:45",
      "dg_id": 18586,
      "open_odds": 171,
      "open_time": "2026-02-02 14:00",
      "outcome": "T16",
      "player_name": "Smith, Jordan"
    },
    {
      "bet_outcome_numeric": 0,
      "bet_outcome_text": "loss",
      "close_odds": 181,
      "close_time": "2026-02-05 07:45",
      "dg_id": 20766,
      "open_odds": 161,
      "open_time": "2026-02-02 14:00",
      "outcome": "CUT",
      "player_name": "Brown, Dan"
    },
    {
      "bet_outcome_numeric": 0,
      "bet_outcome_text": "loss",
      "close_odds": 191,
      "close_time": "2026-02-05 07:45",
      "dg_id": 13764,
      "open_odds": 171,
      "open_time": "2026-02-02 14:00",
      "outcome": "T35",
      "player_name": "Parry, John"
    },
    {
      "bet_outcome_numeric": 0,
      "bet_outcome_text": "loss",
      "close_odds": 196,
      "close_time": "2026-02-05 07:45",
      "dg_id": 29197,
      "open_odds": 271,
      "open_time": "2026-02-02 14:00",
      "outcome": "T48",
      "player_name": "Brennan, Michael"
    },
    {
      "bet_outcome_numeric": 0,
      "bet_outcome_text": "loss",
      "close_odds": 196,
      "close_time": "2026-02-05 07:45",
      "dg_id": 8825,
      "open_odds": 151,
      "open_time": "2026-02-02 14:00",
      "outcome": "CUT",
      "player_name": "Harman, Brian"
    },
    {
      "bet_outcome_numeric": 0,
      "bet_outcome_text": "loss",
      "close_odds": 201,
      "close_time": "2026-02-05 07:45",
      "dg_id": 12808,
      "open_odds": 221,
      "open_time": "2026-02-02 14:00",
      "outcome": "CUT",
      "player_name": "Grillo, Emiliano"
    },
    {
      "bet_outcome_numeric": 0,
      "bet_outcome_text": "loss",
      "close_odds": 201,
      "close_time": "2026-02-05 07:45",
      "dg_id": 14509,
      "open_odds": 211,
      "open_time": "2026-02-02 14:00",
      "outcome": "CUT",
      "player_name": "Dahmen, Joel"
    },
    {
      "bet_outcome_numeric": 0,
      "bet_outcome_text": "loss",
      "close_odds": 211,
      "close_time": "2026-02-05 07:45",
      "dg_id": 12423,
      "open_odds": 161,
      "open_time": "2026-02-02 14:00",
      "outcome": "CUT",
      "player_name": "Kirk, Chris"
    },
    {
      "bet_outcome_numeric": 0,
      "bet_outcome_text": "loss",
      "close_odds": 211,
      "close_time": "2026-02-05 07:45",
      "dg_id": 25908,
      "open_odds": 186,
      "open_time": "2026-02-02 14:00",
      "outcome": "CUT",
      "player_name": "Whaley, Vince"
    },
    {
      "bet_outcome_numeric": 0,
      "bet_outcome_text": "loss",
      "close_odds": 221,
      "close_time": "2026-02-05 07:45",
      "dg_id": 21688,
      "open_odds": 221,
      "open_time": "2026-02-02 14:00",
      "outcome": "T54",
      "player_name": "Kim, S.H."
    },
    {
      "bet_outcome_numeric": 0,
      "bet_outcome_text": "loss",
      "close_odds": 226,
      "close_time": "2026-02-05 07:45",
      "dg_id": 23816,
      "open_odds": 221,
      "open_time": "2026-02-02 14:00",
      "outcome": "T41",
      "player_name": "Valimaki, Sami"
    },
    {
      "bet_outcome_numeric": 0,
      "bet_outcome_text": "loss",
      "close_odds": 231,
      "close_time": "2026-02-05 07:45",
      "dg_id": 12577,
      "open_odds": 231,
      "open_time": "2026-02-02 14:00",
      "outcome": "T64",
      "player_name": "Woodland, Gary"
    },
    {
      "bet_outcome_numeric": 0,
      "bet_outcome_text": "loss",
      "close_odds": 231,
      "close_time": "2026-02-05 07:45",
      "dg_id": 11049,
      "open_odds": 191,
      "open_time": "2026-02-02 14:00",
      "outcome": "CUT",
      "player_name": "Simpson, Webb"
    },
    {
      "bet_outcome_numeric": 0,
      "bet_outcome_text": "loss",
      "close_odds": 241,
      "close_time": "2026-02-05 07:45",
      "dg_id": 20722,
      "open_odds": 196,
      "open_time": "2026-02-02 14:00",
      "outcome": "CUT",
      "player_name": "Schmid, Matti"
    },
    {
      "bet_outcome_numeric": 0,
      "bet_outcome_text": "loss",
      "close_odds": 251,
      "close_time": "2026-02-05 07:45",
      "dg_id": 15556,
      "open_odds": 221,
      "open_time": "2026-02-02 14:00",
      "outcome": "T28",
      "player_name": "Hughes, Mackenzie"
    },
    {
      "bet_outcome_numeric": 0,
      "bet_outcome_text": "loss",
      "close_odds": 261,
      "close_time": "2026-02-05 07:45",
      "dg_id": 24766,
      "open_odds": 301,
      "open_time": "2026-02-02 14:00",
      "outcome": "T35",
      "player_name": "Kim, Tom"
    },
    {
      "bet_outcome_numeric": 0,
      "bet_outcome_text": "loss",
      "close_odds": 261,
      "close_time": "2026-02-05 07:45",
      "dg_id": 29770,
      "open_odds": 251,
      "open_time": "2026-02-02 14:00",
      "outcome": "CUT",
      "player_name": "Mouw, William"
    },
    {
      "bet_outcome_numeric": 0,
      "bet_outcome_text": "loss",
      "close_odds": 261,
      "close_time": "2026-02-05 07:45",
      "dg_id": 11276,
      "open_odds": 231,
      "open_time": "2026-02-02 14:00",
      "outcome": "CUT",
      "player_name": "Horschel, Billy"
    },
    {
      "bet_outcome_numeric": 0,
      "bet_outcome_text": "loss",
      "close_odds": 271,
      "close_time": "2026-02-05 07:45",
      "dg_id": 26653,
      "open_odds": 261,
      "open_time": "2026-02-02 14:00",
      "outcome": "CUT",
      "player_name": "Eckroat, Austin"
    },
    {
      "bet_outcome_numeric": 0,
      "bet_outcome_text": "loss",
      "close_odds": 276,
      "close_time": "2026-02-05 07:45",
      "dg_id": 22833,
      "open_odds": 251,
      "open_time": "2026-02-02 14:00",
      "outcome": "CUT",
      "player_name": "Echavarria, Nico"
    },
    {
      "bet_outcome_numeric": 0,
      "bet_outcome_text": "loss",
      "close_odds": 281,
      "close_time": "2026-02-05 07:45",
      "dg_id": 27900,
      "open_odds": 381,
      "open_time": "2026-02-02 14:00",
      "outcome": "CUT",
      "player_name": "Potgieter, Aldrich"
    },
    {
      "bet_outcome_numeric": 0,
      "bet_outcome_text": "loss",
      "close_odds": 291,
      "close_time": "2026-02-05 07:45",
      "dg_id": 11889,
      "open_odds": 231,
      "open_time": "2026-02-02 14:00",
      "outcome": "T24",
      "player_name": "Fox, Ryan"
    },
    {
      "bet_outcome_numeric": 0,
      "bet_outcome_text": "loss",
      "close_odds": 321,
      "close_time": "2026-02-05 07:45",
      "dg_id": 22002,
      "open_odds": 361,
      "open_time": "2026-02-02 14:00",
      "outcome": "CUT",
      "player_name": "Dumont De Chassart, Adrien"
    },
    {
      "bet_outcome_numeric": 0,
      "bet_outcome_text": "loss",
      "close_odds": 351,
      "close_time": "2026-02-05 07:45",
      "dg_id": 27164,
      "open_odds": 351,
      "open_time": "2026-02-02 14:00",
      "outcome": "T66",
      "player_name": "Phillips, Chandler"
    },
    {
      "bet_outcome_numeric": 0,
      "bet_outcome_text": "loss",
      "close_odds": 351,
      "close_time": "2026-02-05 07:45",
      "dg_id": 22985,
      "open_odds": 301,
      "open_time": "2026-02-02 14:00",
      "outcome": "CUT",
      "player_name": "Smotherman, Austin"
    },
    {
      "bet_outcome_numeric": 0,
      "bet_outcome_text": "loss",
      "close_odds": 361,
      "close_time": "2026-02-05 07:45",
      "dg_id": 16333,
      "open_odds": 341,
      "open_time": "2026-02-02 14:00",
      "outcome": "CUT",
      "player_name": "Hubbard, Mark"
    },
    {
      "bet_outcome_numeric": 0,
      "bet_outcome_text": "loss",
      "close_odds": 361,
      "close_time": "2026-02-05 07:45",
      "dg_id": 15575,
      "open_odds": 291,
      "open_time": "2026-02-02 14:00",
      "outcome": "CUT",
      "player_name": "Hoge, Tom"
    },
    {
      "bet_outcome_numeric": 0,
      "bet_outcome_text": "loss",
      "close_odds": 391,
      "close_time": "2026-02-05 07:45",
      "dg_id": 19729,
      "open_odds": 401,
      "open_time": "2026-02-02 14:00",
      "outcome": "T60",
      "player_name": "Kanaya, Takumi"
    },
    {
      "bet_outcome_numeric": 0,
      "bet_outcome_text": "loss",
      "close_odds": 391,
      "close_time": "2026-02-05 07:45",
      "dg_id": 19840,
      "open_odds": 326,
      "open_time": "2026-02-02 14:00",
      "outcome": "T48",
      "player_name": "Ramey, Chad"
    },
    {
      "bet_outcome_numeric": 0,
      "bet_outcome_text": "loss",
      "close_odds": 401,
      "close_time": "2026-02-05 07:45",
      "dg_id": 24304,
      "open_odds": 401,
      "open_time": "2026-02-02 14:00",
      "outcome": "CUT",
      "player_name": "Vilips, Karl"
    },
    {
      "bet_outcome_numeric": 0,
      "bet_outcome_text": "loss",
      "close_odds": 431,
      "close_time": "2026-02-05 07:45",
      "dg_id": 21074,
      "open_odds": 441,
      "open_time": "2026-02-02 14:00",
      "outcome": "71",
      "player_name": "Nakajima, Keita"
    },
    {
      "bet_outcome_numeric": 0,
      "bet_outcome_text": "loss",
      "close_odds": 441,
      "close_time": "2026-02-05 07:45",
      "dg_id": 18424,
      "open_odds": 381,
      "open_time": "2026-02-02 14:00",
      "outcome": "T13",
      "player_name": "Roy, Kevin"
    },
    {
      "bet_outcome_numeric": 0,
      "bet_outcome_text": "loss",
      "close_odds": 476,
      "close_time": "2026-02-05 07:45",
      "dg_id": 32055,
      "open_odds": 421,
      "open_time": "2026-02-02 14:00",
      "outcome": "T68",
      "player_name": "Shipley, Neal"
    },
    {
      "bet_outcome_numeric": 0,
      "bet_outcome_text": "loss",
      "close_odds": 491,
      "close_time": "2026-02-05 07:45",
      "dg_id": 16757,
      "open_odds": 431,
      "open_time": "2026-02-02 14:00",
      "outcome": "T13",
      "player_name": "Dou, Zecheng"
    },
    {
      "bet_outcome_numeric": 0,
      "bet_outcome_text": "loss",
      "close_odds": 501,
      "close_time": "2026-02-05 07:45",
      "dg_id": 24956,
      "open_odds": 481,
      "open_time": "2026-02-02 14:00",
      "outcome": "CUT",
      "player_name": "Blanchet, Chandler"
    },
    {
      "bet_outcome_numeric": 0,
      "bet_outcome_text": "loss",
      "close_odds": 501,
      "close_time": "2026-02-05 07:45",
      "dg_id": 19960,
      "open_odds": 441,
      "open_time": "2026-02-02 14:00",
      "outcome": "CUT",
      "player_name": "Pavon, Matthieu"
    },
    {
      "bet_outcome_numeric": 0,
      "bet_outcome_text": "loss",
      "close_odds": 501,
      "close_time": "2026-02-05 07:45",
      "dg_id": 14792,
      "open_odds": 481,
      "open_time": "2026-02-02 14:00",
      "outcome": "T60",
      "player_name": "Saddier, Adrien"
    },
    {
      "bet_outcome_numeric": 0,
      "bet_outcome_text": "loss",
      "close_odds": 501,
      "close_time": "2026-02-05 07:45",
      "dg_id": 19872,
      "open_odds": 451,
      "open_time": "2026-02-02 14:00",
      "outcome": "CUT",
      "player_name": "Riley, Davis"
    },
    {
      "bet_outcome_numeric": 0,
      "bet_outcome_text": "loss",
      "close_odds": 601,
      "close_time": "2026-02-05 07:45",
      "dg_id": 19477,
      "open_odds": 626,
      "open_time": "2026-02-02 14:00",
      "outcome": "CUT",
      "player_name": "Schenk, Adam"
    },
    {
      "bet_outcome_numeric": 0,
      "bet_outcome_text": "loss",
      "close_odds": 626,
      "close_time": "2026-02-05 07:45",
      "dg_id": 17550,
      "open_odds": 626,
      "open_time": "2026-02-02 14:00",
      "outcome": "CUT",
      "player_name": "Van Rooyen, Erik"
    },
    {
      "bet_outcome_numeric": 0,
      "bet_outcome_text": "loss",
      "close_odds": 651,
      "close_time": "2026-02-05 07:45",
      "dg_id": 29925,
      "open_odds": 751,
      "open_time": "2026-02-02 14:00",
      "outcome": "T54",
      "player_name": "Yellamaraju, Sudarshan"
    },
    {
      "bet_outcome_numeric": 0,
      "bet_outcome_text": "loss",
      "close_odds": 826,
      "close_time": "2026-02-05 07:45",
      "dg_id": 28016,
      "open_odds": 776,
      "open_time": "2026-02-02 14:00",
      "outcome": "WD",
      "player_name": "Gonzalez, Emilio"
    },
    {
      "bet_outcome_numeric": 0,
      "bet_outcome_text": "loss",
      "close_odds": 851,
      "close_time": "2026-02-05 07:45",
      "dg_id": 19846,
      "open_odds": 801,
      "open_time": "2026-02-02 14:00",
      "outcome": "T48",
      "player_name": "Bauchou, Zach"
    },
    {
      "bet_outcome_numeric": 0,
      "bet_outcome_text": "loss",
      "close_odds": 876,
      "close_time": "2026-02-05 07:45",
      "dg_id": 17786,
      "open_odds": 876,
      "open_time": "2026-02-02 14:00",
      "outcome": "73",
      "player_name": "Davis, Cam"
    },
    {
      "bet_outcome_numeric": 0,
      "bet_outcome_text": "loss",
      "close_odds": 926,
      "close_time": "2026-02-05 07:45",
      "dg_id": 13470,
      "open_odds": 676,
      "open_time": "2026-02-02 14:00",
      "outcome": "72",
      "player_name": "Kizzire, Patton"
    },
    {
      "bet_outcome_numeric": 0,
      "bet_outcome_text": "loss",
      "close_odds": 951,
      "close_time": "2026-02-05 07:45",
      "dg_id": 5768,
      "open_odds": 951,
      "open_time": "2026-02-02 14:00",
      "outcome": "CUT",
      "player_name": "Hoffman, Charley"
    },
    {
      "bet_outcome_numeric": 0,
      "bet_outcome_text": "loss",
      "close_odds": 951,
      "close_time": "2026-02-05 07:45",
      "dg_id": 25319,
      "open_odds": 926,
      "open_time": "2026-02-02 14:00",
      "outcome": "T60",
      "player_name": "VanDerLaan, John"
    },
    {
      "bet_outcome_numeric": 0,
      "bet_outcome_text": "loss",
      "close_odds": 976,
      "close_time": "2026-02-05 07:45",
      "dg_id": 11451,
      "open_odds": 901,
      "open_time": "2026-02-02 14:00",
      "outcome": "CUT",
      "player_name": "Garnett, Brice"
    },
    {
      "bet_outcome_numeric": 0,
      "bet_outcome_text": "loss",
      "close_odds": 976,
      "close_time": "2026-02-05 07:45",
      "dg_id": 16162,
      "open_odds": 801,
      "open_time": "2026-02-02 14:00",
      "outcome": "T48",
      "player_name": "Lee, S.T."
    },
    {
      "bet_outcome_numeric": 0,
      "bet_outcome_text": "loss",
      "close_odds": 1051,
      "close_time": "2026-02-05 07:45",
      "dg_id": 17032,
      "open_odds": 381,
      "open_time": "2026-02-03 08:33",
      "outcome": "CUT",
      "player_name": "Tosti, Alejandro"
    },
    {
      "bet_outcome_numeric": 0,
      "bet_outcome_text": "loss",
      "close_odds": 1201,
      "close_time": "2026-02-05 07:45",
      "dg_id": 20954,
      "open_odds": 1151,
      "open_time": "2026-02-02 14:00",
      "outcome": "T54",
      "player_name": "Hirata, Kensei"
    },
    {
      "bet_outcome_numeric": 0,
      "bet_outcome_text": "loss",
      "close_odds": 1251,
      "close_time": "2026-02-05 07:45",
      "dg_id": 21943,
      "open_odds": 976,
      "open_time": "2026-02-02 14:00",
      "outcome": "T68",
      "player_name": "Lebioda, Hank"
    },
    {
      "bet_outcome_numeric": 0,
      "bet_outcome_text": "loss",
      "close_odds": 1251,
      "close_time": "2026-02-05 07:45",
      "dg_id": 24343,
      "open_odds": 1251,
      "open_time": "2026-02-02 14:00",
      "outcome": "T48",
      "player_name": "Lamprecht, Christo"
    },
    {
      "bet_outcome_numeric": 0,
      "bet_outcome_text": "loss",
      "close_odds": 1351,
      "close_time": "2026-02-05 07:45",
      "dg_id": 25003,
      "open_odds": 1451,
      "open_time": "2026-02-02 14:00",
      "outcome": "CUT",
      "player_name": "Walker, Danny"
    },
    {
      "bet_outcome_numeric": 0,
      "bet_outcome_text": "loss",
      "close_odds": 1401,
      "close_time": "2026-02-05 07:45",
      "dg_id": 30620,
      "open_odds": 1251,
      "open_time": "2026-02-02 14:00",
      "outcome": "CUT",
      "player_name": "Chatfield, Davis"
    },
    {
      "bet_outcome_numeric": 0,
      "bet_outcome_text": "loss",
      "close_odds": 1451,
      "close_time": "2026-02-05 07:45",
      "dg_id": 21883,
      "open_odds": 1151,
      "open_time": "2026-02-03 08:33",
      "outcome": "T28",
      "player_name": "Ewart, A.J."
    },
    {
      "bet_outcome_numeric": 0,
      "bet_outcome_text": "loss",
      "close_odds": 2001,
      "close_time": "2026-02-05 07:45",
      "dg_id": 28469,
      "open_odds": 2001,
      "open_time": "2026-02-02 14:00",
      "outcome": "T54",
      "player_name": "Highsmith, Joe"
    },
    {
      "bet_outcome_numeric": 0,
      "bet_outcome_text": "loss",
      "close_odds": 2001,
      "close_time": "2026-02-05 07:45",
      "dg_id": 25475,
      "open_odds": 1351,
      "open_time": "2026-02-03 08:33",
      "outcome": "CUT",
      "player_name": "Nyholm, Pontus"
    },
    {
      "bet_outcome_numeric": 0,
      "bet_outcome_text": "loss",
      "close_odds": 2251,
      "close_time": "2026-02-05 07:45",
      "dg_id": 18628,
      "open_odds": 2251,
      "open_time": "2026-02-02 14:00",
      "outcome": "T54",
      "player_name": "Campbell, Brian"
    },
    {
      "bet_outcome_numeric": 0,
      "bet_outcome_text": "loss",
      "close_odds": 2501,
      "close_time": "2026-02-05 07:45",
      "dg_id": 21889,
      "open_odds": 2001,
      "open_time": "2026-02-02 14:00",
      "outcome": "CUT",
      "player_name": "Kang, Jeffrey"
    },
    {
      "bet_outcome_numeric": 0,
      "bet_outcome_text": "loss",
      "close_odds": 2751,
      "close_time": "2026-02-05 07:45",
      "dg_id": 16591,
      "open_odds": 2751,
      "open_time": "2026-02-05 07:45",
      "outcome": "CUT",
      "player_name": "Rozo, Marcelo"
    },
    {
      "bet_outcome_numeric": 0,
      "bet_outcome_text": "loss",
      "close_odds": 2751,
      "close_time": "2026-02-05 07:45",
      "dg_id": 14926,
      "open_odds": 2501,
      "open_time": "2026-02-02 14:00",
      "outcome": "CUT",
      "player_name": "Malnati, Peter"
    },
    {
      "bet_outcome_numeric": 0,
      "bet_outcome_text": "loss",
      "close_odds": 3501,
      "close_time": "2026-02-05 07:45",
      "dg_id": 12909,
      "open_odds": 4001,
      "open_time": "2026-02-02 14:00",
      "outcome": "CUT",
      "player_name": "Campos, Rafael"
    },
    {
      "bet_outcome_numeric": 0,
      "bet_outcome_text": "loss",
      "close_odds": 5001,
      "close_time": "2026-02-05 07:45",
      "dg_id": 31585,
      "open_odds": 4501,
      "open_time": "2026-02-02 14:00",
      "outcome": "CUT",
      "player_name": "Avant, Thomas"
    }
  ],
  "season": 2026,
  "year": 2026
}